{"ts":["help_texts_rgba-0-tr:1024x2048"],"ss":[{"n":"sco_panel_1_001","t":0,"sx":312,"sy":1901,"sw":40,"sh":14,"dx":2,"dy":50,"dw":64,"dh":64},{"n":"sco_panel_1_002","t":0,"sx":184,"sy":1855,"sw":33,"sh":63,"dx":31,"dy":1,"dw":64,"dh":64},{"n":"sco_panel_1_003","t":0,"sx":463,"sy":397,"sw":64,"sh":63,"dy":1,"dw":64,"dh":64},{"n":"sco_panel_1_004","t":0,"sx":529,"sy":397,"sw":64,"sh":63,"dy":1,"dw":64,"dh":64},{"n":"sco_panel_1_005","t":0,"sx":595,"sy":397,"sw":64,"sh":63,"dy":1,"dw":64,"dh":64},{"n":"sco_panel_1_006","t":0,"sx":661,"sy":397,"sw":64,"sh":63,"dy":1,"dw":64,"dh":64},{"n":"sco_panel_1_007","t":0,"sx":1,"sy":1,"sw":64,"sh":64,"dw":64,"dh":64},{"n":"sco_panel_1_008","t":0,"sx":727,"sy":397,"sw":64,"sh":63,"dy":1,"dw":64,"dh":64},{"n":"sco_panel_1_009","t":0,"sx":793,"sy":397,"sw":64,"sh":63,"dy":1,"dw":64,"dh":64},{"n":"sco_panel_1_010","t":0,"sx":859,"sy":397,"sw":64,"sh":63,"dy":1,"dw":64,"dh":64},{"n":"sco_panel_1_011","t":0,"sx":67,"sy":1,"sw":64,"sh":64,"dw":64,"dh":64},{"n":"sco_panel_1_012","t":0,"sx":175,"sy":1926,"sw":46,"sh":64,"dw":64,"dh":64},{"n":"sco_panel_1_013","t":0,"sx":530,"sy":1808,"sw":33,"sh":16,"dx":31,"dw":64,"dh":64},{"n":"sco_panel_1_014","t":0,"sx":199,"sy":1535,"sw":64,"sh":17,"dw":64,"dh":64},{"n":"sco_panel_1_015","t":0,"sx":397,"sy":1571,"sw":64,"sh":16,"dw":64,"dh":64},{"n":"sco_panel_1_016","t":0,"sx":67,"sy":1536,"sw":64,"sh":17,"dw":64,"dh":64},{"n":"sco_panel_1_017","t":0,"sx":1,"sy":1537,"sw":64,"sh":17,"dw":64,"dh":64},{"n":"sco_panel_1_018","t":0,"sx":133,"sy":1536,"sw":64,"sh":17,"dw":64,"dh":64},{"n":"sco_panel_1_019","t":0,"sx":67,"sy":1555,"sw":64,"sh":16,"dw":64,"dh":64},{"n":"sco_panel_1_020","t":0,"sx":331,"sy":1533,"sw":64,"sh":17,"dw":64,"dh":64},{"n":"sco_panel_1_021","t":0,"sx":397,"sy":1533,"sw":64,"sh":17,"dw":64,"dh":64},{"n":"sco_panel_1_022","t":0,"sx":463,"sy":1536,"sw":64,"sh":17,"dw":64,"dh":64},{"n":"sco_panel_1_023","t":0,"sx":53,"sy":1855,"sw":45,"sh":17,"dw":64,"dh":64},{"n":"sco_panel_1_024","t":0,"sx":1017,"sy":655,"sw":5,"sh":30,"dx":59,"dy":32,"dw":64,"dh":64},{"n":"sco_panel_1_025","t":0,"sx":397,"sy":1131,"sw":64,"sh":32,"dy":32,"dw":64,"dh":64},{"n":"sco_panel_1_026","t":0,"sx":199,"sy":1252,"sw":64,"sh":25,"dy":38,"dw":64,"dh":64},{"n":"sco_panel_1_027","t":0,"sx":727,"sy":1434,"sw":64,"sh":20,"dy":43,"dw":64,"dh":64},{"n":"sco_panel_1_028","t":0,"sx":725,"sy":1666,"sw":63,"sh":25,"dy":38,"dw":64,"dh":64},{"n":"sco_panel_1_029","t":0,"sx":212,"sy":1992,"sw":57,"sh":25,"dx":7,"dy":38,"dw":64,"dh":64},{"n":"sco_panel_1_030","t":0,"sx":265,"sy":1255,"sw":64,"sh":25,"dy":38,"dw":64,"dh":64},{"n":"sco_panel_1_031","t":0,"sx":199,"sy":1279,"sw":64,"sh":25,"dy":38,"dw":64,"dh":64},{"n":"sco_panel_1_032","t":0,"sx":67,"sy":1280,"sw":64,"sh":25,"dy":38,"dw":64,"dh":64},{"n":"sco_panel_1_033","t":0,"sx":397,"sy":1229,"sw":64,"sh":26,"dy":38,"dw":64,"dh":64},{"n":"sco_panel_1_034","t":0,"sx":1,"sy":1281,"sw":64,"sh":25,"dy":38,"dw":64,"dh":64},{"n":"sco_panel_1_035","t":0,"sx":133,"sy":1280,"sw":64,"sh":25,"dy":38,"dw":64,"dh":64},{"n":"sco_panel_1_036","t":0,"sx":256,"sy":2019,"sw":57,"sh":25,"dx":7,"dy":38,"dw":64,"dh":64},{"n":"sco_panel_1_037","t":0,"sx":661,"sy":1435,"sw":64,"sh":20,"dy":43,"dw":64,"dh":64},{"n":"sco_panel_1_038","t":0,"sx":331,"sy":1257,"sw":64,"sh":25,"dy":38,"dw":64,"dh":64},{"n":"sco_panel_1_039","t":0,"sx":463,"sy":1236,"sw":64,"sh":26,"dy":38,"dw":64,"dh":64},{"n":"sco_panel_1_040","t":0,"sx":529,"sy":1242,"sw":64,"sh":26,"dy":38,"dw":64,"dh":64},{"n":"sco_panel_1_041","t":0,"sx":265,"sy":1282,"sw":64,"sh":25,"dy":38,"dw":64,"dh":64},{"n":"sco_panel_1_042","t":0,"sx":1008,"sy":848,"sw":15,"sh":20,"dy":44,"dw":64,"dh":64},{"n":"sco_panel_1_043","t":0,"sx":1012,"sy":961,"sw":5,"sh":24,"dx":59,"dy":9,"dw":64,"dh":64},{"n":"sco_panel_1_044","t":0,"sx":105,"sy":1815,"sw":56,"sh":34,"dw":64,"dh":64},{"n":"sco_panel_1_045","t":0,"sx":199,"sy":1306,"sw":64,"sh":25,"dy":9,"dw":64,"dh":64},{"n":"sco_panel_1_046","t":0,"sx":67,"sy":1096,"sw":64,"sh":30,"dy":9,"dw":64,"dh":64},{"n":"sco_panel_1_047","t":0,"sx":634,"sy":1731,"sw":58,"sh":25,"dy":9,"dw":64,"dh":64},{"n":"sco_panel_1_048","t":0,"sx":129,"sy":1702,"sw":61,"sh":25,"dx":3,"dy":9,"dw":64,"dh":64},{"n":"sco_panel_1_049","t":0,"sx":595,"sy":1250,"sw":64,"sh":26,"dy":8,"dw":64,"dh":64},{"n":"sco_panel_1_050","t":0,"sx":315,"sy":2019,"sw":54,"sh":25,"dx":1,"dy":9,"dw":64,"dh":64},{"n":"sco_panel_1_051","t":0,"sx":397,"sy":1257,"sw":64,"sh":25,"dy":9,"dw":64,"dh":64},{"n":"sco_panel_1_052","t":0,"sx":925,"sy":1218,"sw":64,"sh":39,"dw":64,"dh":64},{"n":"sco_panel_1_053","t":0,"sx":59,"sy":1874,"sw":39,"sh":24,"dy":9,"dw":64,"dh":64},{"n":"sco_panel_1_054","t":0,"sx":991,"sy":968,"sw":8,"sh":4,"dx":56,"dw":64,"dh":64},{"n":"sco_panel_1_055","t":0,"sx":1001,"sy":969,"sw":5,"sh":4,"dx":8,"dw":64,"dh":64},{"n":"sco_panel_1_056","t":0,"sx":1016,"sy":687,"sw":7,"sh":6,"dx":57,"dy":57,"dw":64,"dh":64},{"n":"sco_panel_1_057","t":0,"sx":64,"sy":1742,"sw":61,"sh":7,"dy":57,"dw":64,"dh":64},{"n":"sco_panel_1_058","t":0,"sx":991,"sy":342,"sw":28,"sh":7,"dx":2,"dy":57,"dw":64,"dh":64},{"n":"sco_panel_1_059","t":0,"sx":986,"sy":1633,"sw":37,"sh":7,"dx":10,"dy":57,"dw":64,"dh":64},{"n":"sco_panel_1_060","t":0,"sx":756,"sy":1724,"sw":59,"sh":2,"dx":3,"dy":62,"dw":64,"dh":64},{"n":"sco_panel_1_061","t":0,"sx":286,"sy":1917,"sw":54,"sh":7,"dx":7,"dy":57,"dw":64,"dh":64},{"n":"sco_panel_1_062","t":0,"sx":1,"sy":2040,"sw":55,"sh":7,"dx":9,"dy":57,"dw":64,"dh":64},{"n":"sco_panel_1_063","t":0,"sx":456,"sy":1837,"sw":41,"sh":7,"dy":57,"dw":64,"dh":64},{"n":"sco_panel_1_064","t":0,"sx":876,"sy":1784,"sw":35,"sh":7,"dx":6,"dy":57,"dw":64,"dh":64},{"n":"sco_panel_1_065","t":0,"sx":63,"sy":1789,"sw":60,"sh":7,"dx":4,"dy":57,"dw":64,"dh":64},{"n":"sco_panel_1_066","t":0,"sx":695,"sy":1720,"sw":59,"sh":7,"dy":57,"dw":64,"dh":64},{"n":"sco_panel_1_067","t":0,"sx":105,"sy":1851,"sw":57,"sh":2,"dx":2,"dy":62,"dw":64,"dh":64},{"n":"sco_panel_1_068","t":0,"sx":368,"sy":1874,"sw":52,"sh":7,"dx":5,"dy":57,"dw":64,"dh":64},{"n":"sco_panel_1_069","t":0,"sx":368,"sy":1892,"sw":46,"sh":7,"dx":7,"dy":57,"dw":64,"dh":64},{"n":"sco_panel_1_070","t":0,"sx":354,"sy":1901,"sw":49,"sh":8,"dx":15,"dy":56,"dw":64,"dh":64},{"n":"sco_panel_1_071","t":0,"sx":368,"sy":1883,"sw":52,"sh":7,"dx":12,"dy":57,"dw":64,"dh":64},{"n":"sco_panel_1_072","t":0,"sx":342,"sy":1917,"sw":54,"sh":7,"dy":57,"dw":64,"dh":64},{"n":"sco_panel_1_073","t":0,"sx":412,"sy":1846,"sw":43,"sh":7,"dx":13,"dy":57,"dw":64,"dh":64},{"n":"sco_panel_1_074","t":0,"sx":661,"sy":1581,"sw":64,"sh":7,"dy":57,"dw":64,"dh":64},{"n":"sco_panel_1_075","t":0,"sx":371,"sy":1855,"sw":46,"sh":7,"dx":16,"dy":57,"dw":64,"dh":64},{"n":"sco_panel_1_076","t":0,"sx":991,"sy":974,"sw":5,"sh":2,"dx":2,"dy":62,"dw":64,"dh":64},{"n":"sco_panel_1_077","t":0,"sx":1012,"sy":961,"sw":5,"sh":24,"dx":59,"dy":28,"dw":64,"dh":64},{"n":"sco_panel_1_078","t":0,"sx":859,"sy":884,"sw":64,"sh":53,"dw":64,"dh":64},{"n":"sco_panel_1_079","t":0,"sx":925,"sy":885,"sw":64,"sh":53,"dw":64,"dh":64},{"n":"sco_panel_1_080","t":0,"sx":529,"sy":885,"sw":64,"sh":53,"dw":64,"dh":64},{"n":"sco_panel_1_081","t":0,"sx":331,"sy":652,"sw":64,"sh":58,"dw":64,"dh":64},{"n":"sco_panel_1_082","t":0,"sx":595,"sy":885,"sw":64,"sh":53,"dw":64,"dh":64},{"n":"sco_panel_1_083","t":0,"sx":661,"sy":885,"sw":64,"sh":53,"dw":64,"dh":64},{"n":"sco_panel_1_084","t":0,"sx":727,"sy":885,"sw":64,"sh":53,"dw":64,"dh":64},{"n":"sco_panel_1_085","t":0,"sx":793,"sy":885,"sw":64,"sh":53,"dw":64,"dh":64},{"n":"sco_panel_1_086","t":0,"sx":859,"sy":939,"sw":64,"sh":53,"dw":64,"dh":64},{"n":"sco_panel_1_087","t":0,"sx":925,"sy":940,"sw":64,"sh":53,"dw":64,"dh":64},{"n":"sco_panel_1_088","t":0,"sx":463,"sy":651,"sw":64,"sh":58,"dw":64,"dh":64},{"n":"sco_panel_1_089","t":0,"sx":1,"sy":1630,"sw":62,"sh":53,"dw":64,"dh":64},{"n":"sco_panel_1_090","t":0,"sx":571,"sy":1784,"sw":57,"sh":18,"dx":7,"dw":64,"dh":64},{"n":"sco_panel_1_091","t":0,"sx":463,"sy":1496,"sw":64,"sh":18,"dw":64,"dh":64},{"n":"sco_panel_1_092","t":0,"sx":529,"sy":1498,"sw":64,"sh":18,"dw":64,"dh":64},{"n":"sco_panel_1_093","t":0,"sx":595,"sy":1501,"sw":64,"sh":18,"dw":64,"dh":64},{"n":"sco_panel_1_094","t":0,"sx":661,"sy":1501,"sw":64,"sh":18,"dw":64,"dh":64},{"n":"sco_panel_1_095","t":0,"sx":265,"sy":1513,"sw":64,"sh":18,"dw":64,"dh":64},{"n":"sco_panel_1_096","t":0,"sx":199,"sy":1515,"sw":64,"sh":18,"dw":64,"dh":64},{"n":"sco_panel_1_097","t":0,"sx":1007,"sy":942,"sw":11,"sh":17,"dw":64,"dh":64},{"n":"sco_panel_2_001","t":0,"sx":1007,"sy":932,"sw":13,"sh":3,"dx":51,"dy":61,"dw":64,"dh":64},{"n":"sco_panel_2_002","t":0,"sx":377,"sy":1756,"sw":51,"sh":3,"dy":61,"dw":64,"dh":64},{"n":"sco_panel_2_003","t":0,"sx":1,"sy":1756,"sw":61,"sh":3,"dx":3,"dy":61,"dw":64,"dh":64},{"n":"sco_panel_2_004","t":0,"sx":529,"sy":1604,"sw":64,"sh":2,"dy":62,"dw":64,"dh":64},{"n":"sco_panel_2_005","t":0,"sx":793,"sy":1589,"sw":64,"sh":3,"dy":61,"dw":64,"dh":64},{"n":"sco_panel_2_006","t":0,"sx":925,"sy":1591,"sw":64,"sh":3,"dy":61,"dw":64,"dh":64},{"n":"sco_panel_2_007","t":0,"sx":859,"sy":1593,"sw":64,"sh":3,"dy":61,"dw":64,"dh":64},{"n":"sco_panel_2_008","t":0,"sx":925,"sy":1596,"sw":64,"sh":3,"dy":61,"dw":64,"dh":64},{"n":"sco_panel_2_009","t":0,"sx":991,"sy":696,"sw":23,"sh":2,"dy":62,"dw":64,"dh":64},{"n":"sco_panel_2_010","t":0,"sx":266,"sy":1926,"sw":40,"sh":64,"dx":24,"dw":64,"dh":64},{"n":"sco_panel_2_011","t":0,"sx":133,"sy":1,"sw":64,"sh":64,"dw":64,"dh":64},{"n":"sco_panel_2_012","t":0,"sx":199,"sy":1,"sw":64,"sh":64,"dw":64,"dh":64},{"n":"sco_panel_2_013","t":0,"sx":265,"sy":1,"sw":64,"sh":64,"dw":64,"dh":64},{"n":"sco_panel_2_014","t":0,"sx":331,"sy":1,"sw":64,"sh":64,"dw":64,"dh":64},{"n":"sco_panel_2_015","t":0,"sx":397,"sy":1,"sw":64,"sh":64,"dw":64,"dh":64},{"n":"sco_panel_2_016","t":0,"sx":463,"sy":1,"sw":64,"sh":64,"dw":64,"dh":64},{"n":"sco_panel_2_017","t":0,"sx":529,"sy":1,"sw":64,"sh":64,"dw":64,"dh":64},{"n":"sco_panel_2_018","t":0,"sx":60,"sy":1926,"sw":56,"sh":64,"dw":64,"dh":64},{"n":"sco_panel_2_019","t":0,"sx":986,"sy":1642,"sw":36,"sh":20,"dx":28,"dw":64,"dh":64},{"n":"sco_panel_2_020","t":0,"sx":925,"sy":1417,"sw":64,"sh":20,"dw":64,"dh":64},{"n":"sco_panel_2_021","t":0,"sx":859,"sy":1418,"sw":64,"sh":20,"dw":64,"dh":64},{"n":"sco_panel_2_022","t":0,"sx":793,"sy":1435,"sw":64,"sh":20,"dw":64,"dh":64},{"n":"sco_panel_2_023","t":0,"sx":727,"sy":1456,"sw":64,"sh":20,"dw":64,"dh":64},{"n":"sco_panel_2_024","t":0,"sx":925,"sy":1439,"sw":64,"sh":20,"dw":64,"dh":64},{"n":"sco_panel_2_025","t":0,"sx":859,"sy":1440,"sw":64,"sh":20,"dw":64,"dh":64},{"n":"sco_panel_2_026","t":0,"sx":793,"sy":1457,"sw":64,"sh":20,"dw":64,"dh":64},{"n":"sco_panel_2_027","t":0,"sx":1021,"sy":327,"sw":2,"sh":10,"dw":64,"dh":64},{"n":"sco_panel_2_028","t":0,"sx":1,"sy":1992,"sw":50,"sh":46,"dx":14,"dy":18,"dw":64,"dh":64},{"n":"sco_panel_2_029","t":0,"sx":661,"sy":991,"sw":64,"sh":45,"dy":19,"dw":64,"dh":64},{"n":"sco_panel_2_030","t":0,"sx":595,"sy":992,"sw":64,"sh":45,"dy":19,"dw":64,"dh":64},{"n":"sco_panel_2_031","t":0,"sx":529,"sy":993,"sw":64,"sh":45,"dy":19,"dw":64,"dh":64},{"n":"sco_panel_2_032","t":0,"sx":793,"sy":988,"sw":64,"sh":45,"dy":19,"dw":64,"dh":64},{"n":"sco_panel_2_033","t":0,"sx":859,"sy":994,"sw":64,"sh":45,"dy":19,"dw":64,"dh":64},{"n":"sco_panel_2_034","t":0,"sx":661,"sy":1176,"sw":64,"sh":40,"dy":24,"dw":64,"dh":64},{"n":"sco_panel_2_035","t":0,"sx":793,"sy":1035,"sw":64,"sh":45,"dy":19,"dw":64,"dh":64},{"n":"sco_panel_2_036","t":0,"sx":595,"sy":1177,"sw":64,"sh":40,"dy":24,"dw":64,"dh":64},{"n":"sco_panel_2_037","t":0,"sx":727,"sy":1036,"sw":64,"sh":45,"dy":19,"dw":64,"dh":64},{"n":"sco_panel_2_038","t":0,"sx":661,"sy":1038,"sw":64,"sh":45,"dy":19,"dw":64,"dh":64},{"n":"sco_panel_2_039","t":0,"sx":595,"sy":1039,"sw":64,"sh":45,"dy":19,"dw":64,"dh":64},{"n":"sco_panel_2_040","t":0,"sx":529,"sy":1040,"sw":64,"sh":45,"dy":19,"dw":64,"dh":64},{"n":"sco_panel_2_041","t":0,"sx":660,"sy":1666,"sw":63,"sh":45,"dy":19,"dw":64,"dh":64},{"n":"sco_panel_2_042","t":0,"sx":1008,"sy":821,"sw":15,"sh":25,"dy":19,"dw":64,"dh":64},{"n":"sco_panel_2_043","t":0,"sx":1,"sy":1815,"sw":50,"sh":57,"dx":14,"dw":64,"dh":64},{"n":"sco_panel_2_044","t":0,"sx":595,"sy":1,"sw":64,"sh":64,"dw":64,"dh":64},{"n":"sco_panel_2_045","t":0,"sx":661,"sy":1,"sw":64,"sh":64,"dw":64,"dh":64},{"n":"sco_panel_2_046","t":0,"sx":727,"sy":1,"sw":64,"sh":64,"dw":64,"dh":64},{"n":"sco_panel_2_047","t":0,"sx":793,"sy":1,"sw":64,"sh":64,"dw":64,"dh":64},{"n":"sco_panel_2_048","t":0,"sx":859,"sy":1,"sw":64,"sh":64,"dw":64,"dh":64},{"n":"sco_panel_2_049","t":0,"sx":265,"sy":883,"sw":64,"sh":51,"dw":64,"dh":64},{"n":"sco_panel_2_050","t":0,"sx":331,"sy":883,"sw":64,"sh":51,"dw":64,"dh":64},{"n":"sco_panel_2_051","t":0,"sx":397,"sy":883,"sw":64,"sh":51,"dw":64,"dh":64},{"n":"sco_panel_2_052","t":0,"sx":925,"sy":771,"sw":64,"sh":56,"dw":64,"dh":64},{"n":"sco_panel_2_053","t":0,"sx":463,"sy":886,"sw":64,"sh":51,"dw":64,"dh":64},{"n":"sco_panel_2_054","t":0,"sx":463,"sy":770,"sw":64,"sh":56,"dw":64,"dh":64},{"n":"sco_panel_2_055","t":0,"sx":793,"sy":1129,"sw":64,"sh":42,"dw":64,"dh":64},{"n":"sco_panel_2_056","t":0,"sx":530,"sy":1786,"sw":33,"sh":20,"dw":64,"dh":64},{"n":"sco_panel_2_057","t":0,"sx":427,"sy":1761,"sw":49,"sh":20,"dx":15,"dy":2,"dw":64,"dh":64},{"n":"sco_panel_2_058","t":0,"sx":331,"sy":1445,"sw":64,"sh":22,"dw":64,"dh":64},{"n":"sco_panel_2_059","t":0,"sx":331,"sy":1199,"sw":64,"sh":27,"dw":64,"dh":64},{"n":"sco_panel_2_060","t":0,"sx":727,"sy":1363,"sw":64,"sh":22,"dw":64,"dh":64},{"n":"sco_panel_2_061","t":0,"sx":859,"sy":1348,"sw":64,"sh":22,"dw":64,"dh":64},{"n":"sco_panel_2_062","t":0,"sx":793,"sy":1365,"sw":64,"sh":22,"dw":64,"dh":64},{"n":"sco_panel_2_063","t":0,"sx":1007,"sy":911,"sw":13,"sh":19,"dy":2,"dw":64,"dh":64},{"n":"sco_panel_2_064","t":0,"sx":219,"sy":1855,"sw":49,"sh":61,"dx":15,"dy":3,"dw":64,"dh":64},{"n":"sco_panel_2_065","t":0,"sx":925,"sy":588,"sw":64,"sh":60,"dy":4,"dw":64,"dh":64},{"n":"sco_panel_2_066","t":0,"sx":925,"sy":650,"sw":64,"sh":60,"dy":4,"dw":64,"dh":64},{"n":"sco_panel_2_067","t":0,"sx":1,"sy":528,"sw":64,"sh":60,"dy":4,"dw":64,"dh":64},{"n":"sco_panel_2_068","t":0,"sx":67,"sy":528,"sw":64,"sh":60,"dy":4,"dw":64,"dh":64},{"n":"sco_panel_2_069","t":0,"sx":133,"sy":528,"sw":64,"sh":60,"dy":4,"dw":64,"dh":64},{"n":"sco_panel_2_070","t":0,"sx":199,"sy":528,"sw":64,"sh":60,"dy":4,"dw":64,"dh":64},{"n":"sco_panel_2_071","t":0,"sx":265,"sy":528,"sw":64,"sh":60,"dy":4,"dw":64,"dh":64},{"n":"sco_panel_2_072","t":0,"sx":529,"sy":828,"sw":64,"sh":55,"dy":9,"dw":64,"dh":64},{"n":"sco_panel_2_073","t":0,"sx":331,"sy":528,"sw":64,"sh":60,"dy":4,"dw":64,"dh":64},{"n":"sco_panel_2_074","t":0,"sx":397,"sy":528,"sw":64,"sh":60,"dy":4,"dw":64,"dh":64},{"n":"sco_panel_2_075","t":0,"sx":1,"sy":590,"sw":64,"sh":60,"dy":4,"dw":64,"dh":64},{"n":"sco_panel_2_076","t":0,"sx":67,"sy":590,"sw":64,"sh":60,"dy":4,"dw":64,"dh":64},{"n":"sco_panel_2_077","t":0,"sx":66,"sy":1628,"sw":62,"sh":59,"dy":4,"dw":64,"dh":64},{"n":"sco_panel_2_078","t":0,"sx":1017,"sy":648,"sw":6,"sh":5,"dx":30,"dw":64,"dh":64},{"n":"sco_panel_2_079","t":0,"sx":53,"sy":1815,"sw":50,"sh":36,"dx":14,"dy":22,"dw":64,"dh":64},{"n":"sco_panel_2_080","t":0,"sx":463,"sy":1264,"sw":64,"sh":25,"dy":28,"dw":64,"dh":64},{"n":"sco_panel_2_081","t":0,"sx":925,"sy":1461,"sw":64,"sh":20,"dy":33,"dw":64,"dh":64},{"n":"sco_panel_2_082","t":0,"sx":529,"sy":1270,"sw":64,"sh":25,"dy":28,"dw":64,"dh":64},{"n":"sco_panel_2_083","t":0,"sx":859,"sy":1462,"sw":64,"sh":20,"dy":33,"dw":64,"dh":64},{"n":"sco_panel_2_084","t":0,"sx":65,"sy":1689,"sw":62,"sh":25,"dy":28,"dw":64,"dh":64},{"n":"sco_panel_2_085","t":0,"sx":595,"sy":1278,"sw":64,"sh":25,"dy":28,"dw":64,"dh":64},{"n":"sco_panel_2_086","t":0,"sx":661,"sy":1255,"sw":64,"sh":26,"dy":27,"dw":64,"dh":64},{"n":"sco_panel_2_087","t":0,"sx":925,"sy":1259,"sw":64,"sh":36,"dy":28,"dw":64,"dh":64},{"n":"sco_panel_2_088","t":0,"sx":133,"sy":1096,"sw":64,"sh":30,"dy":28,"dw":64,"dh":64},{"n":"sco_panel_2_089","t":0,"sx":67,"sy":1307,"sw":64,"sh":25,"dy":28,"dw":64,"dh":64},{"n":"sco_panel_2_090","t":0,"sx":1,"sy":1308,"sw":64,"sh":25,"dy":28,"dw":64,"dh":64},{"n":"sco_panel_2_091","t":0,"sx":790,"sy":1670,"sw":63,"sh":25,"dy":28,"dw":64,"dh":64},{"n":"sco_panel_2_092","t":0,"sx":253,"sy":1785,"sw":52,"sh":64,"dx":12,"dw":64,"dh":64},{"n":"sco_panel_2_093","t":0,"sx":133,"sy":590,"sw":64,"sh":60,"dw":64,"dh":64},{"n":"sco_panel_2_094","t":0,"sx":595,"sy":828,"sw":64,"sh":55,"dy":4,"dw":64,"dh":64},{"n":"sco_panel_2_095","t":0,"sx":397,"sy":590,"sw":64,"sh":59,"dw":64,"dh":64},{"n":"sco_panel_2_096","t":0,"sx":859,"sy":1297,"sw":64,"sh":24,"dw":64,"dh":64},{"n":"sco_panel_2_097","t":0,"sx":397,"sy":1198,"sw":64,"sh":29,"dw":64,"dh":64},{"n":"sco_panel_2_098","t":0,"sx":463,"sy":1205,"sw":64,"sh":29,"dw":64,"dh":64},{"n":"sco_panel_2_099","t":0,"sx":793,"sy":1314,"sw":64,"sh":24,"dw":64,"dh":64},{"n":"sco_panel_2_100","t":0,"sx":197,"sy":1573,"sw":63,"sh":24,"dx":1,"dw":64,"dh":64},{"n":"sco_panel_2_101","t":0,"sx":925,"sy":1297,"sw":64,"sh":24,"dw":64,"dh":64},{"n":"sco_panel_2_102","t":0,"sx":661,"sy":1337,"sw":64,"sh":24,"dw":64,"dh":64},{"n":"sco_panel_2_103","t":0,"sx":529,"sy":1211,"sw":64,"sh":29,"dw":64,"dh":64},{"n":"sco_panel_2_104","t":0,"sx":65,"sy":1716,"sw":61,"sh":24,"dx":2,"dw":64,"dh":64},{"n":"sco_panel_3_001","t":0,"sx":196,"sy":1622,"sw":63,"sh":2,"dx":1,"dy":62,"dw":64,"dh":64},{"n":"sco_panel_3_002","t":0,"sx":259,"sy":1685,"sw":62,"sh":3,"dy":61,"dw":64,"dh":64},{"n":"sco_panel_3_003","t":0,"sx":154,"sy":2020,"sw":55,"sh":3,"dx":9,"dy":61,"dw":64,"dh":64},{"n":"sco_panel_3_004","t":0,"sx":595,"sy":1590,"sw":64,"sh":3,"dy":61,"dw":64,"dh":64},{"n":"sco_panel_3_005","t":0,"sx":529,"sy":1594,"sw":64,"sh":3,"dy":61,"dw":64,"dh":64},{"n":"sco_panel_3_006","t":0,"sx":661,"sy":1590,"sw":64,"sh":3,"dy":61,"dw":64,"dh":64},{"n":"sco_panel_3_007","t":0,"sx":727,"sy":1590,"sw":64,"sh":3,"dy":61,"dw":64,"dh":64},{"n":"sco_panel_3_008","t":0,"sx":793,"sy":1594,"sw":64,"sh":3,"dy":61,"dw":64,"dh":64},{"n":"sco_panel_3_009","t":0,"sx":859,"sy":1598,"sw":64,"sh":3,"dy":61,"dw":64,"dh":64},{"n":"sco_panel_3_010","t":0,"sx":925,"sy":1601,"sw":64,"sh":3,"dy":61,"dw":64,"dh":64},{"n":"sco_panel_3_011","t":0,"sx":595,"sy":1595,"sw":64,"sh":3,"dy":61,"dw":64,"dh":64},{"n":"sco_panel_3_012","t":0,"sx":450,"sy":1692,"sw":60,"sh":3,"dy":61,"dw":64,"dh":64},{"n":"sco_panel_3_013","t":0,"sx":451,"sy":1680,"sw":62,"sh":2,"dx":2,"dy":62,"dw":64,"dh":64},{"n":"sco_panel_3_014","t":0,"sx":529,"sy":1599,"sw":64,"sh":3,"dy":61,"dw":64,"dh":64},{"n":"sco_panel_3_015","t":0,"sx":450,"sy":1697,"sw":60,"sh":3,"dy":61,"dw":64,"dh":64},{"n":"sco_panel_3_016","t":0,"sx":163,"sy":1847,"sw":56,"sh":2,"dx":8,"dy":62,"dw":64,"dh":64},{"n":"sco_panel_3_017","t":0,"sx":463,"sy":1600,"sw":64,"sh":3,"dy":61,"dw":64,"dh":64},{"n":"sco_panel_3_018","t":0,"sx":991,"sy":737,"sw":20,"sh":3,"dy":61,"dw":64,"dh":64},{"n":"sco_panel_3_019","t":0,"sx":991,"sy":880,"sw":14,"sh":64,"dx":50,"dw":64,"dh":64},{"n":"sco_panel_3_020","t":0,"sx":925,"sy":1,"sw":64,"sh":64,"dw":64,"dh":64},{"n":"sco_panel_3_021","t":0,"sx":1,"sy":67,"sw":64,"sh":64,"dw":64,"dh":64},{"n":"sco_panel_3_022","t":0,"sx":67,"sy":67,"sw":64,"sh":64,"dw":64,"dh":64},{"n":"sco_panel_3_023","t":0,"sx":133,"sy":67,"sw":64,"sh":64,"dw":64,"dh":64},{"n":"sco_panel_3_024","t":0,"sx":199,"sy":67,"sw":64,"sh":64,"dw":64,"dh":64},{"n":"sco_panel_3_025","t":0,"sx":265,"sy":67,"sw":64,"sh":64,"dw":64,"dh":64},{"n":"sco_panel_3_026","t":0,"sx":331,"sy":67,"sw":64,"sh":64,"dw":64,"dh":64},{"n":"sco_panel_3_027","t":0,"sx":397,"sy":67,"sw":64,"sh":64,"dw":64,"dh":64},{"n":"sco_panel_3_028","t":0,"sx":463,"sy":67,"sw":64,"sh":64,"dw":64,"dh":64},{"n":"sco_panel_3_029","t":0,"sx":529,"sy":67,"sw":64,"sh":64,"dw":64,"dh":64},{"n":"sco_panel_3_030","t":0,"sx":595,"sy":67,"sw":64,"sh":64,"dw":64,"dh":64},{"n":"sco_panel_3_031","t":0,"sx":661,"sy":67,"sw":64,"sh":64,"dw":64,"dh":64},{"n":"sco_panel_3_032","t":0,"sx":727,"sy":67,"sw":64,"sh":64,"dw":64,"dh":64},{"n":"sco_panel_3_033","t":0,"sx":793,"sy":67,"sw":64,"sh":64,"dw":64,"dh":64},{"n":"sco_panel_3_034","t":0,"sx":859,"sy":67,"sw":64,"sh":64,"dw":64,"dh":64},{"n":"sco_panel_3_035","t":0,"sx":925,"sy":67,"sw":64,"sh":64,"dw":64,"dh":64},{"n":"sco_panel_3_036","t":0,"sx":1,"sy":133,"sw":64,"sh":64,"dw":64,"dh":64},{"n":"sco_panel_3_037","t":0,"sx":991,"sy":38,"sw":29,"sh":64,"dw":64,"dh":64},{"n":"sco_panel_3_038","t":0,"sx":1007,"sy":890,"sw":14,"sh":19,"dx":50,"dw":64,"dh":64},{"n":"sco_panel_3_039","t":0,"sx":925,"sy":1483,"sw":64,"sh":20,"dw":64,"dh":64},{"n":"sco_panel_3_040","t":0,"sx":595,"sy":1457,"sw":64,"sh":20,"dw":64,"dh":64},{"n":"sco_panel_3_041","t":0,"sx":925,"sy":1348,"sw":64,"sh":21,"dw":64,"dh":64},{"n":"sco_panel_3_042","t":0,"sx":661,"sy":1457,"sw":64,"sh":20,"dw":64,"dh":64},{"n":"sco_panel_3_043","t":0,"sx":925,"sy":1371,"sw":64,"sh":21,"dw":64,"dh":64},{"n":"sco_panel_3_044","t":0,"sx":859,"sy":1372,"sw":64,"sh":21,"dw":64,"dh":64},{"n":"sco_panel_3_045","t":0,"sx":727,"sy":1478,"sw":64,"sh":20,"dw":64,"dh":64},{"n":"sco_panel_3_046","t":0,"sx":793,"sy":1479,"sw":64,"sh":20,"dw":64,"dh":64},{"n":"sco_panel_3_047","t":0,"sx":859,"sy":1484,"sw":64,"sh":20,"dw":64,"dh":64},{"n":"sco_panel_3_048","t":0,"sx":105,"sy":2025,"sw":57,"sh":20,"dw":64,"dh":64},{"n":"sco_panel_3_049","t":0,"sx":986,"sy":1611,"sw":37,"sh":20,"dx":27,"dw":64,"dh":64},{"n":"sco_panel_3_050","t":0,"sx":925,"sy":1505,"sw":64,"sh":20,"dw":64,"dh":64},{"n":"sco_panel_3_051","t":0,"sx":265,"sy":1469,"sw":64,"sh":20,"dw":64,"dh":64},{"n":"sco_panel_3_052","t":0,"sx":331,"sy":1469,"sw":64,"sh":20,"dw":64,"dh":64},{"n":"sco_panel_3_053","t":0,"sx":397,"sy":1469,"sw":64,"sh":20,"dw":64,"dh":64},{"n":"sco_panel_3_054","t":0,"sx":463,"sy":1474,"sw":64,"sh":20,"dw":64,"dh":64},{"n":"sco_panel_3_055","t":0,"sx":529,"sy":1476,"sw":64,"sh":20,"dw":64,"dh":64},{"n":"sco_panel_3_056","t":0,"sx":991,"sy":282,"sw":29,"sh":21,"dw":64,"dh":64},{"n":"sco_panel_3_057","t":0,"sx":110,"sy":1992,"sw":42,"sh":31,"dx":22,"dy":33,"dw":64,"dh":64},{"n":"sco_panel_3_058","t":0,"sx":133,"sy":1307,"sw":64,"sh":25,"dy":34,"dw":64,"dh":64},{"n":"sco_panel_3_059","t":0,"sx":331,"sy":1284,"sw":64,"sh":25,"dy":34,"dw":64,"dh":64},{"n":"sco_panel_3_060","t":0,"sx":265,"sy":1309,"sw":64,"sh":25,"dy":34,"dw":64,"dh":64},{"n":"sco_panel_3_061","t":0,"sx":199,"sy":1333,"sw":64,"sh":25,"dy":34,"dw":64,"dh":64},{"n":"sco_panel_3_062","t":0,"sx":397,"sy":1284,"sw":64,"sh":25,"dy":34,"dw":64,"dh":64},{"n":"sco_panel_3_063","t":0,"sx":463,"sy":1291,"sw":64,"sh":25,"dy":39,"dw":64,"dh":64},{"n":"sco_panel_3_064","t":0,"sx":816,"sy":1750,"sw":35,"sh":19,"dy":39,"dw":64,"dh":64},{"n":"sco_panel_3_065","t":0,"sx":358,"sy":1794,"sw":41,"sh":25,"dx":23,"dy":30,"dw":64,"dh":64},{"n":"sco_panel_3_066","t":0,"sx":727,"sy":1255,"sw":64,"sh":26,"dy":29,"dw":64,"dh":64},{"n":"sco_panel_3_067","t":0,"sx":195,"sy":1626,"sw":62,"sh":25,"dy":30,"dw":64,"dh":64},{"n":"sco_panel_3_068","t":0,"sx":386,"sy":1734,"sw":59,"sh":20,"dx":5,"dy":35,"dw":64,"dh":64},{"n":"sco_panel_3_069","t":0,"sx":529,"sy":1297,"sw":64,"sh":25,"dy":30,"dw":64,"dh":64},{"n":"sco_panel_3_070","t":0,"sx":970,"sy":1899,"sw":53,"sh":25,"dx":9,"dy":30,"dw":64,"dh":64},{"n":"sco_panel_3_071","t":0,"sx":271,"sy":1992,"sw":56,"sh":25,"dx":8,"dy":30,"dw":64,"dh":64},{"n":"sco_panel_3_072","t":0,"sx":595,"sy":1479,"sw":64,"sh":20,"dy":35,"dw":64,"dh":64},{"n":"sco_panel_3_073","t":0,"sx":725,"sy":1693,"sw":63,"sh":25,"dx":1,"dy":30,"dw":64,"dh":64},{"n":"sco_panel_3_074","t":0,"sx":67,"sy":1334,"sw":64,"sh":25,"dy":30,"dw":64,"dh":64},{"n":"sco_panel_3_075","t":0,"sx":1,"sy":1335,"sw":64,"sh":25,"dy":30,"dw":64,"dh":64},{"n":"sco_panel_3_076","t":0,"sx":133,"sy":1334,"sw":64,"sh":25,"dy":30,"dw":64,"dh":64},{"n":"sco_panel_3_077","t":0,"sx":331,"sy":1311,"sw":64,"sh":25,"dy":35,"dw":64,"dh":64},{"n":"sco_panel_3_078","t":0,"sx":259,"sy":1637,"sw":62,"sh":25,"dy":35,"dw":64,"dh":64},{"n":"sco_panel_3_079","t":0,"sx":486,"sy":1816,"sw":41,"sh":19,"dx":23,"dy":45,"dw":64,"dh":64},{"n":"sco_panel_3_080","t":0,"sx":661,"sy":1479,"sw":64,"sh":20,"dy":44,"dw":64,"dh":64},{"n":"sco_panel_3_081","t":0,"sx":259,"sy":1664,"sw":62,"sh":19,"dy":45,"dw":64,"dh":64},{"n":"sco_panel_3_082","t":0,"sx":914,"sy":1767,"sw":58,"sh":19,"dx":6,"dy":45,"dw":64,"dh":64},{"n":"sco_panel_3_083","t":0,"sx":727,"sy":1500,"sw":64,"sh":20,"dy":44,"dw":64,"dh":64},{"n":"sco_panel_3_084","t":0,"sx":793,"sy":1501,"sw":64,"sh":20,"dy":44,"dw":64,"dh":64},{"n":"sco_panel_3_085","t":0,"sx":316,"sy":1761,"sw":57,"sh":20,"dy":44,"dw":64,"dh":64},{"n":"sco_panel_3_086","t":0,"sx":1,"sy":1717,"sw":61,"sh":19,"dy":45,"dw":64,"dh":64},{"n":"sco_panel_3_087","t":0,"sx":991,"sy":616,"sw":26,"sh":19,"dy":45,"dw":64,"dh":64},{"n":"sco_panel_3_088","t":0,"sx":223,"sy":1926,"sw":41,"sh":64,"dx":23,"dw":64,"dh":64},{"n":"sco_panel_3_089","t":0,"sx":67,"sy":133,"sw":64,"sh":64,"dw":64,"dh":64},{"n":"sco_panel_3_090","t":0,"sx":133,"sy":133,"sw":64,"sh":64,"dw":64,"dh":64},{"n":"sco_panel_3_091","t":0,"sx":199,"sy":133,"sw":64,"sh":64,"dw":64,"dh":64},{"n":"sco_panel_3_092","t":0,"sx":265,"sy":133,"sw":64,"sh":64,"dw":64,"dh":64},{"n":"sco_panel_3_093","t":0,"sx":331,"sy":133,"sw":64,"sh":64,"dw":64,"dh":64},{"n":"sco_panel_3_094","t":0,"sx":397,"sy":133,"sw":64,"sh":64,"dw":64,"dh":64},{"n":"sco_panel_3_095","t":0,"sx":463,"sy":133,"sw":64,"sh":64,"dw":64,"dh":64},{"n":"sco_panel_3_096","t":0,"sx":529,"sy":133,"sw":64,"sh":64,"dw":64,"dh":64},{"n":"sco_panel_3_097","t":0,"sx":265,"sy":1444,"sw":64,"sh":23,"dy":41,"dw":64,"dh":64},{"n":"sco_panel_3_098","t":0,"sx":727,"sy":1387,"sw":64,"sh":22,"dy":42,"dw":64,"dh":64},{"n":"sco_panel_3_099","t":0,"sx":58,"sy":2025,"sw":45,"sh":22,"dy":42,"dw":64,"dh":64},{"n":"sco_panel_3_100","t":0,"sx":100,"sy":1855,"sw":41,"sh":63,"dx":23,"dw":64,"dh":64},{"n":"sco_panel_3_101","t":0,"sx":925,"sy":397,"sw":64,"sh":63,"dw":64,"dh":64},{"n":"sco_panel_3_102","t":0,"sx":463,"sy":462,"sw":64,"sh":63,"dw":64,"dh":64},{"n":"sco_panel_3_103","t":0,"sx":595,"sy":133,"sw":64,"sh":64,"dw":64,"dh":64},{"n":"sco_panel_3_104","t":0,"sx":661,"sy":133,"sw":64,"sh":64,"dw":64,"dh":64},{"n":"sco_panel_3_105","t":0,"sx":1,"sy":463,"sw":64,"sh":63,"dw":64,"dh":64},{"n":"sco_panel_3_106","t":0,"sx":856,"sy":1608,"sw":63,"sh":63,"dx":1,"dw":64,"dh":64},{"n":"sco_panel_3_107","t":0,"sx":727,"sy":133,"sw":64,"sh":64,"dw":64,"dh":64},{"n":"sco_panel_3_108","t":0,"sx":67,"sy":463,"sw":64,"sh":63,"dw":64,"dh":64},{"n":"sco_panel_3_109","t":0,"sx":133,"sy":463,"sw":64,"sh":63,"dw":64,"dh":64},{"n":"sco_panel_3_110","t":0,"sx":695,"sy":1729,"sw":58,"sh":63,"dw":64,"dh":64},{"n":"sco_panel_3_111","t":0,"sx":199,"sy":463,"sw":64,"sh":63,"dw":64,"dh":64},{"n":"sco_panel_3_112","t":0,"sx":991,"sy":763,"sw":18,"sh":20,"dy":43,"dw":64,"dh":64},{"n":"sco_panel_3_113","t":0,"sx":485,"sy":1794,"sw":43,"sh":20,"dx":21,"dy":15,"dw":64,"dh":64},{"n":"sco_panel_3_114","t":0,"sx":265,"sy":1336,"sw":64,"sh":25,"dy":10,"dw":64,"dh":64},{"n":"sco_panel_3_115","t":0,"sx":199,"sy":1096,"sw":64,"sh":30,"dy":10,"dw":64,"dh":64},{"n":"sco_panel_3_116","t":0,"sx":661,"sy":1218,"sw":64,"sh":35,"dw":64,"dh":64},{"n":"sco_panel_3_117","t":0,"sx":727,"sy":1218,"sw":64,"sh":35,"dw":64,"dh":64},{"n":"sco_panel_3_118","t":0,"sx":199,"sy":1360,"sw":64,"sh":25,"dy":10,"dw":64,"dh":64},{"n":"sco_panel_3_119","t":0,"sx":397,"sy":1311,"sw":64,"sh":25,"dy":10,"dw":64,"dh":64},{"n":"sco_panel_3_120","t":0,"sx":265,"sy":1095,"sw":64,"sh":35,"dw":64,"dh":64},{"n":"sco_panel_3_121","t":0,"sx":307,"sy":1821,"sw":48,"sh":25,"dy":10,"dw":64,"dh":64},{"n":"sco_panel_4_001","t":0,"sx":196,"sy":1622,"sw":63,"sh":2,"dx":1,"dy":62,"dw":64,"dh":64},{"n":"sco_panel_4_002","t":0,"sx":259,"sy":1685,"sw":62,"sh":3,"dy":61,"dw":64,"dh":64},{"n":"sco_panel_4_003","t":0,"sx":154,"sy":2020,"sw":55,"sh":3,"dx":9,"dy":61,"dw":64,"dh":64},{"n":"sco_panel_4_004","t":0,"sx":595,"sy":1590,"sw":64,"sh":3,"dy":61,"dw":64,"dh":64},{"n":"sco_panel_4_005","t":0,"sx":529,"sy":1594,"sw":64,"sh":3,"dy":61,"dw":64,"dh":64},{"n":"sco_panel_4_006","t":0,"sx":661,"sy":1590,"sw":64,"sh":3,"dy":61,"dw":64,"dh":64},{"n":"sco_panel_4_007","t":0,"sx":727,"sy":1590,"sw":64,"sh":3,"dy":61,"dw":64,"dh":64},{"n":"sco_panel_4_008","t":0,"sx":793,"sy":1594,"sw":64,"sh":3,"dy":61,"dw":64,"dh":64},{"n":"sco_panel_4_009","t":0,"sx":859,"sy":1598,"sw":64,"sh":3,"dy":61,"dw":64,"dh":64},{"n":"sco_panel_4_010","t":0,"sx":925,"sy":1601,"sw":64,"sh":3,"dy":61,"dw":64,"dh":64},{"n":"sco_panel_4_011","t":0,"sx":595,"sy":1595,"sw":64,"sh":3,"dy":61,"dw":64,"dh":64},{"n":"sco_panel_4_012","t":0,"sx":450,"sy":1692,"sw":60,"sh":3,"dy":61,"dw":64,"dh":64},{"n":"sco_panel_4_013","t":0,"sx":451,"sy":1680,"sw":62,"sh":2,"dx":2,"dy":62,"dw":64,"dh":64},{"n":"sco_panel_4_014","t":0,"sx":529,"sy":1599,"sw":64,"sh":3,"dy":61,"dw":64,"dh":64},{"n":"sco_panel_4_015","t":0,"sx":450,"sy":1697,"sw":60,"sh":3,"dy":61,"dw":64,"dh":64},{"n":"sco_panel_4_016","t":0,"sx":163,"sy":1847,"sw":56,"sh":2,"dx":8,"dy":62,"dw":64,"dh":64},{"n":"sco_panel_4_017","t":0,"sx":463,"sy":1600,"sw":64,"sh":3,"dy":61,"dw":64,"dh":64},{"n":"sco_panel_4_018","t":0,"sx":991,"sy":737,"sw":20,"sh":3,"dy":61,"dw":64,"dh":64},{"n":"sco_panel_4_019","t":0,"sx":991,"sy":880,"sw":14,"sh":64,"dx":50,"dw":64,"dh":64},{"n":"sco_panel_4_020","t":0,"sx":925,"sy":1,"sw":64,"sh":64,"dw":64,"dh":64},{"n":"sco_panel_4_021","t":0,"sx":1,"sy":67,"sw":64,"sh":64,"dw":64,"dh":64},{"n":"sco_panel_4_022","t":0,"sx":67,"sy":67,"sw":64,"sh":64,"dw":64,"dh":64},{"n":"sco_panel_4_023","t":0,"sx":133,"sy":67,"sw":64,"sh":64,"dw":64,"dh":64},{"n":"sco_panel_4_024","t":0,"sx":199,"sy":67,"sw":64,"sh":64,"dw":64,"dh":64},{"n":"sco_panel_4_025","t":0,"sx":265,"sy":67,"sw":64,"sh":64,"dw":64,"dh":64},{"n":"sco_panel_4_026","t":0,"sx":331,"sy":67,"sw":64,"sh":64,"dw":64,"dh":64},{"n":"sco_panel_4_027","t":0,"sx":397,"sy":67,"sw":64,"sh":64,"dw":64,"dh":64},{"n":"sco_panel_4_028","t":0,"sx":463,"sy":67,"sw":64,"sh":64,"dw":64,"dh":64},{"n":"sco_panel_4_029","t":0,"sx":529,"sy":67,"sw":64,"sh":64,"dw":64,"dh":64},{"n":"sco_panel_4_030","t":0,"sx":595,"sy":67,"sw":64,"sh":64,"dw":64,"dh":64},{"n":"sco_panel_4_031","t":0,"sx":661,"sy":67,"sw":64,"sh":64,"dw":64,"dh":64},{"n":"sco_panel_4_032","t":0,"sx":727,"sy":67,"sw":64,"sh":64,"dw":64,"dh":64},{"n":"sco_panel_4_033","t":0,"sx":793,"sy":67,"sw":64,"sh":64,"dw":64,"dh":64},{"n":"sco_panel_4_034","t":0,"sx":859,"sy":67,"sw":64,"sh":64,"dw":64,"dh":64},{"n":"sco_panel_4_035","t":0,"sx":925,"sy":67,"sw":64,"sh":64,"dw":64,"dh":64},{"n":"sco_panel_4_036","t":0,"sx":1,"sy":133,"sw":64,"sh":64,"dw":64,"dh":64},{"n":"sco_panel_4_037","t":0,"sx":991,"sy":38,"sw":29,"sh":64,"dw":64,"dh":64},{"n":"sco_panel_4_038","t":0,"sx":1007,"sy":890,"sw":14,"sh":19,"dx":50,"dw":64,"dh":64},{"n":"sco_panel_4_039","t":0,"sx":925,"sy":1483,"sw":64,"sh":20,"dw":64,"dh":64},{"n":"sco_panel_4_040","t":0,"sx":595,"sy":1457,"sw":64,"sh":20,"dw":64,"dh":64},{"n":"sco_panel_4_041","t":0,"sx":925,"sy":1348,"sw":64,"sh":21,"dw":64,"dh":64},{"n":"sco_panel_4_042","t":0,"sx":661,"sy":1457,"sw":64,"sh":20,"dw":64,"dh":64},{"n":"sco_panel_4_043","t":0,"sx":925,"sy":1371,"sw":64,"sh":21,"dw":64,"dh":64},{"n":"sco_panel_4_044","t":0,"sx":859,"sy":1372,"sw":64,"sh":21,"dw":64,"dh":64},{"n":"sco_panel_4_045","t":0,"sx":727,"sy":1478,"sw":64,"sh":20,"dw":64,"dh":64},{"n":"sco_panel_4_046","t":0,"sx":793,"sy":1479,"sw":64,"sh":20,"dw":64,"dh":64},{"n":"sco_panel_4_047","t":0,"sx":859,"sy":1484,"sw":64,"sh":20,"dw":64,"dh":64},{"n":"sco_panel_4_048","t":0,"sx":105,"sy":2025,"sw":57,"sh":20,"dw":64,"dh":64},{"n":"sco_panel_4_049","t":0,"sx":986,"sy":1611,"sw":37,"sh":20,"dx":27,"dw":64,"dh":64},{"n":"sco_panel_4_050","t":0,"sx":925,"sy":1505,"sw":64,"sh":20,"dw":64,"dh":64},{"n":"sco_panel_4_051","t":0,"sx":265,"sy":1469,"sw":64,"sh":20,"dw":64,"dh":64},{"n":"sco_panel_4_052","t":0,"sx":331,"sy":1469,"sw":64,"sh":20,"dw":64,"dh":64},{"n":"sco_panel_4_053","t":0,"sx":397,"sy":1469,"sw":64,"sh":20,"dw":64,"dh":64},{"n":"sco_panel_4_054","t":0,"sx":463,"sy":1474,"sw":64,"sh":20,"dw":64,"dh":64},{"n":"sco_panel_4_055","t":0,"sx":529,"sy":1476,"sw":64,"sh":20,"dw":64,"dh":64},{"n":"sco_panel_4_056","t":0,"sx":991,"sy":282,"sw":29,"sh":21,"dw":64,"dh":64},{"n":"sco_panel_4_057","t":0,"sx":211,"sy":2020,"sw":43,"sh":26,"dx":21,"dy":32,"dw":64,"dh":64},{"n":"sco_panel_4_058","t":0,"sx":463,"sy":1318,"sw":64,"sh":25,"dy":33,"dw":64,"dh":64},{"n":"sco_panel_4_059","t":0,"sx":67,"sy":1361,"sw":64,"sh":25,"dy":33,"dw":64,"dh":64},{"n":"sco_panel_4_060","t":0,"sx":595,"sy":1219,"sw":64,"sh":29,"dy":33,"dw":64,"dh":64},{"n":"sco_panel_4_061","t":0,"sx":793,"sy":1259,"sw":64,"sh":26,"dy":32,"dw":64,"dh":64},{"n":"sco_panel_4_062","t":0,"sx":67,"sy":1128,"sw":64,"sh":30,"dy":33,"dw":64,"dh":64},{"n":"sco_panel_4_063","t":0,"sx":571,"sy":1762,"sw":58,"sh":20,"dy":38,"dw":64,"dh":64},{"n":"sco_panel_4_064","t":0,"sx":195,"sy":1653,"sw":62,"sh":25,"dx":2,"dy":33,"dw":64,"dh":64},{"n":"sco_panel_4_065","t":0,"sx":855,"sy":1673,"sw":63,"sh":25,"dx":1,"dy":33,"dw":64,"dh":64},{"n":"sco_panel_4_066","t":0,"sx":1,"sy":1362,"sw":64,"sh":25,"dy":33,"dw":64,"dh":64},{"n":"sco_panel_4_067","t":0,"sx":53,"sy":1992,"sw":55,"sh":31,"dx":9,"dy":33,"dw":64,"dh":64},{"n":"sco_panel_4_068","t":0,"sx":1,"sy":1129,"sw":64,"sh":30,"dy":33,"dw":64,"dh":64},{"n":"sco_panel_4_069","t":0,"sx":133,"sy":1361,"sw":64,"sh":25,"dy":33,"dw":64,"dh":64},{"n":"sco_panel_4_070","t":0,"sx":859,"sy":1506,"sw":64,"sh":20,"dy":38,"dw":64,"dh":64},{"n":"sco_panel_4_071","t":0,"sx":817,"sy":1724,"sw":35,"sh":24,"dy":33,"dw":64,"dh":64},{"n":"sco_panel_4_072","t":0,"sx":1011,"sy":777,"sw":12,"sh":42,"dx":52,"dy":22,"dw":64,"dh":64},{"n":"sco_panel_4_073","t":0,"sx":254,"sy":1738,"sw":60,"sh":42,"dy":22,"dw":64,"dh":64},{"n":"sco_panel_4_074","t":0,"sx":193,"sy":1692,"sw":61,"sh":42,"dx":3,"dy":22,"dw":64,"dh":64},{"n":"sco_panel_4_075","t":0,"sx":925,"sy":1042,"sw":64,"sh":43,"dy":21,"dw":64,"dh":64},{"n":"sco_panel_4_076","t":0,"sx":727,"sy":1130,"sw":64,"sh":42,"dy":22,"dw":64,"dh":64},{"n":"sco_panel_4_077","t":0,"sx":925,"sy":1087,"sw":64,"sh":43,"dy":21,"dw":64,"dh":64},{"n":"sco_panel_4_078","t":0,"sx":661,"sy":1132,"sw":64,"sh":42,"dy":22,"dw":64,"dh":64},{"n":"sco_panel_4_079","t":0,"sx":925,"sy":1176,"sw":64,"sh":40,"dy":24,"dw":64,"dh":64},{"n":"sco_panel_4_080","t":0,"sx":595,"sy":1133,"sw":64,"sh":42,"dy":22,"dw":64,"dh":64},{"n":"sco_panel_4_081","t":0,"sx":191,"sy":1747,"sw":60,"sh":42,"dy":22,"dw":64,"dh":64},{"n":"sco_panel_4_082","t":0,"sx":127,"sy":1752,"sw":60,"sh":42,"dx":4,"dy":22,"dw":64,"dh":64},{"n":"sco_panel_4_083","t":0,"sx":859,"sy":1088,"sw":64,"sh":43,"dy":21,"dw":64,"dh":64},{"n":"sco_panel_4_084","t":0,"sx":859,"sy":1219,"sw":64,"sh":37,"dy":27,"dw":64,"dh":64},{"n":"sco_panel_4_085","t":0,"sx":859,"sy":1258,"sw":64,"sh":37,"dy":27,"dw":64,"dh":64},{"n":"sco_panel_4_086","t":0,"sx":529,"sy":1134,"sw":64,"sh":42,"dy":22,"dw":64,"dh":64},{"n":"sco_panel_4_087","t":0,"sx":859,"sy":1177,"sw":64,"sh":40,"dy":24,"dw":64,"dh":64},{"n":"sco_panel_4_088","t":0,"sx":925,"sy":1132,"sw":64,"sh":42,"dy":22,"dw":64,"dh":64},{"n":"sco_panel_4_089","t":0,"sx":859,"sy":1133,"sw":64,"sh":42,"dy":22,"dw":64,"dh":64},{"n":"sco_panel_4_090","t":0,"sx":793,"sy":1173,"sw":64,"sh":42,"dy":22,"dw":64,"dh":64},{"n":"sco_panel_4_091","t":0,"sx":727,"sy":1174,"sw":64,"sh":42,"dy":22,"dw":64,"dh":64},{"n":"sco_panel_4_092","t":0,"sx":991,"sy":6,"sw":31,"sh":30,"dy":22,"dw":64,"dh":64},{"n":"sco_panel_4_093","t":0,"sx":1008,"sy":870,"sw":15,"sh":18,"dx":49,"dw":64,"dh":64},{"n":"sco_panel_4_094","t":0,"sx":199,"sy":1468,"sw":64,"sh":23,"dw":64,"dh":64},{"n":"sco_panel_4_095","t":0,"sx":67,"sy":1516,"sw":64,"sh":18,"dw":64,"dh":64},{"n":"sco_panel_4_096","t":0,"sx":1,"sy":1517,"sw":64,"sh":18,"dw":64,"dh":64},{"n":"sco_panel_4_097","t":0,"sx":133,"sy":1516,"sw":64,"sh":18,"dw":64,"dh":64},{"n":"sco_panel_4_098","t":0,"sx":331,"sy":1513,"sw":64,"sh":18,"dw":64,"dh":64},{"n":"sco_panel_4_099","t":0,"sx":397,"sy":1513,"sw":64,"sh":18,"dw":64,"dh":64},{"n":"sco_panel_4_100","t":0,"sx":630,"sy":1785,"sw":57,"sh":18,"dw":64,"dh":64},{"n":"sco_panel_4_101","t":0,"sx":463,"sy":1516,"sw":64,"sh":18,"dw":64,"dh":64},{"n":"sco_panel_4_102","t":0,"sx":308,"sy":1926,"sw":54,"sh":18,"dx":2,"dw":64,"dh":64},{"n":"sco_panel_4_103","t":0,"sx":397,"sy":1419,"sw":64,"sh":23,"dw":64,"dh":64},{"n":"sco_panel_4_104","t":0,"sx":529,"sy":1518,"sw":64,"sh":18,"dw":64,"dh":64},{"n":"sco_panel_4_105","t":0,"sx":595,"sy":1521,"sw":64,"sh":18,"dw":64,"dh":64},{"n":"sco_panel_4_106","t":0,"sx":661,"sy":1521,"sw":64,"sh":18,"dw":64,"dh":64},{"n":"sco_panel_4_107","t":0,"sx":727,"sy":1522,"sw":64,"sh":18,"dw":64,"dh":64},{"n":"sco_panel_4_108","t":0,"sx":67,"sy":1469,"sw":64,"sh":23,"dw":64,"dh":64},{"n":"sco_panel_4_109","t":0,"sx":1,"sy":1470,"sw":64,"sh":23,"dw":64,"dh":64},{"n":"sco_panel_4_110","t":0,"sx":793,"sy":1523,"sw":64,"sh":18,"dw":64,"dh":64},{"n":"sco_panel_4_111","t":0,"sx":859,"sy":1528,"sw":64,"sh":18,"dw":64,"dh":64},{"n":"sco_panel_4_112","t":0,"sx":991,"sy":677,"sw":23,"sh":17,"dw":64,"dh":64},{"n":"sco_panel_5_001","t":0,"sx":196,"sy":1622,"sw":63,"sh":2,"dx":1,"dy":62,"dw":64,"dh":64},{"n":"sco_panel_5_002","t":0,"sx":259,"sy":1685,"sw":62,"sh":3,"dy":61,"dw":64,"dh":64},{"n":"sco_panel_5_003","t":0,"sx":154,"sy":2020,"sw":55,"sh":3,"dx":9,"dy":61,"dw":64,"dh":64},{"n":"sco_panel_5_004","t":0,"sx":595,"sy":1590,"sw":64,"sh":3,"dy":61,"dw":64,"dh":64},{"n":"sco_panel_5_005","t":0,"sx":529,"sy":1594,"sw":64,"sh":3,"dy":61,"dw":64,"dh":64},{"n":"sco_panel_5_006","t":0,"sx":661,"sy":1590,"sw":64,"sh":3,"dy":61,"dw":64,"dh":64},{"n":"sco_panel_5_007","t":0,"sx":727,"sy":1590,"sw":64,"sh":3,"dy":61,"dw":64,"dh":64},{"n":"sco_panel_5_008","t":0,"sx":793,"sy":1594,"sw":64,"sh":3,"dy":61,"dw":64,"dh":64},{"n":"sco_panel_5_009","t":0,"sx":859,"sy":1598,"sw":64,"sh":3,"dy":61,"dw":64,"dh":64},{"n":"sco_panel_5_010","t":0,"sx":925,"sy":1601,"sw":64,"sh":3,"dy":61,"dw":64,"dh":64},{"n":"sco_panel_5_011","t":0,"sx":595,"sy":1595,"sw":64,"sh":3,"dy":61,"dw":64,"dh":64},{"n":"sco_panel_5_012","t":0,"sx":450,"sy":1692,"sw":60,"sh":3,"dy":61,"dw":64,"dh":64},{"n":"sco_panel_5_013","t":0,"sx":451,"sy":1680,"sw":62,"sh":2,"dx":2,"dy":62,"dw":64,"dh":64},{"n":"sco_panel_5_014","t":0,"sx":529,"sy":1599,"sw":64,"sh":3,"dy":61,"dw":64,"dh":64},{"n":"sco_panel_5_015","t":0,"sx":450,"sy":1697,"sw":60,"sh":3,"dy":61,"dw":64,"dh":64},{"n":"sco_panel_5_016","t":0,"sx":163,"sy":1847,"sw":56,"sh":2,"dx":8,"dy":62,"dw":64,"dh":64},{"n":"sco_panel_5_017","t":0,"sx":463,"sy":1600,"sw":64,"sh":3,"dy":61,"dw":64,"dh":64},{"n":"sco_panel_5_018","t":0,"sx":991,"sy":737,"sw":20,"sh":3,"dy":61,"dw":64,"dh":64},{"n":"sco_panel_5_019","t":0,"sx":991,"sy":880,"sw":14,"sh":64,"dx":50,"dw":64,"dh":64},{"n":"sco_panel_5_020","t":0,"sx":925,"sy":1,"sw":64,"sh":64,"dw":64,"dh":64},{"n":"sco_panel_5_021","t":0,"sx":1,"sy":67,"sw":64,"sh":64,"dw":64,"dh":64},{"n":"sco_panel_5_022","t":0,"sx":67,"sy":67,"sw":64,"sh":64,"dw":64,"dh":64},{"n":"sco_panel_5_023","t":0,"sx":133,"sy":67,"sw":64,"sh":64,"dw":64,"dh":64},{"n":"sco_panel_5_024","t":0,"sx":199,"sy":67,"sw":64,"sh":64,"dw":64,"dh":64},{"n":"sco_panel_5_025","t":0,"sx":265,"sy":67,"sw":64,"sh":64,"dw":64,"dh":64},{"n":"sco_panel_5_026","t":0,"sx":331,"sy":67,"sw":64,"sh":64,"dw":64,"dh":64},{"n":"sco_panel_5_027","t":0,"sx":397,"sy":67,"sw":64,"sh":64,"dw":64,"dh":64},{"n":"sco_panel_5_028","t":0,"sx":463,"sy":67,"sw":64,"sh":64,"dw":64,"dh":64},{"n":"sco_panel_5_029","t":0,"sx":529,"sy":67,"sw":64,"sh":64,"dw":64,"dh":64},{"n":"sco_panel_5_030","t":0,"sx":595,"sy":67,"sw":64,"sh":64,"dw":64,"dh":64},{"n":"sco_panel_5_031","t":0,"sx":661,"sy":67,"sw":64,"sh":64,"dw":64,"dh":64},{"n":"sco_panel_5_032","t":0,"sx":727,"sy":67,"sw":64,"sh":64,"dw":64,"dh":64},{"n":"sco_panel_5_033","t":0,"sx":793,"sy":67,"sw":64,"sh":64,"dw":64,"dh":64},{"n":"sco_panel_5_034","t":0,"sx":859,"sy":67,"sw":64,"sh":64,"dw":64,"dh":64},{"n":"sco_panel_5_035","t":0,"sx":925,"sy":67,"sw":64,"sh":64,"dw":64,"dh":64},{"n":"sco_panel_5_036","t":0,"sx":1,"sy":133,"sw":64,"sh":64,"dw":64,"dh":64},{"n":"sco_panel_5_037","t":0,"sx":991,"sy":38,"sw":29,"sh":64,"dw":64,"dh":64},{"n":"sco_panel_5_038","t":0,"sx":1007,"sy":890,"sw":14,"sh":19,"dx":50,"dw":64,"dh":64},{"n":"sco_panel_5_039","t":0,"sx":925,"sy":1483,"sw":64,"sh":20,"dw":64,"dh":64},{"n":"sco_panel_5_040","t":0,"sx":595,"sy":1457,"sw":64,"sh":20,"dw":64,"dh":64},{"n":"sco_panel_5_041","t":0,"sx":925,"sy":1348,"sw":64,"sh":21,"dw":64,"dh":64},{"n":"sco_panel_5_042","t":0,"sx":661,"sy":1457,"sw":64,"sh":20,"dw":64,"dh":64},{"n":"sco_panel_5_043","t":0,"sx":925,"sy":1371,"sw":64,"sh":21,"dw":64,"dh":64},{"n":"sco_panel_5_044","t":0,"sx":859,"sy":1372,"sw":64,"sh":21,"dw":64,"dh":64},{"n":"sco_panel_5_045","t":0,"sx":727,"sy":1478,"sw":64,"sh":20,"dw":64,"dh":64},{"n":"sco_panel_5_046","t":0,"sx":793,"sy":1479,"sw":64,"sh":20,"dw":64,"dh":64},{"n":"sco_panel_5_047","t":0,"sx":859,"sy":1484,"sw":64,"sh":20,"dw":64,"dh":64},{"n":"sco_panel_5_048","t":0,"sx":105,"sy":2025,"sw":57,"sh":20,"dw":64,"dh":64},{"n":"sco_panel_5_049","t":0,"sx":986,"sy":1611,"sw":37,"sh":20,"dx":27,"dw":64,"dh":64},{"n":"sco_panel_5_050","t":0,"sx":925,"sy":1505,"sw":64,"sh":20,"dw":64,"dh":64},{"n":"sco_panel_5_051","t":0,"sx":265,"sy":1469,"sw":64,"sh":20,"dw":64,"dh":64},{"n":"sco_panel_5_052","t":0,"sx":331,"sy":1469,"sw":64,"sh":20,"dw":64,"dh":64},{"n":"sco_panel_5_053","t":0,"sx":397,"sy":1469,"sw":64,"sh":20,"dw":64,"dh":64},{"n":"sco_panel_5_054","t":0,"sx":463,"sy":1474,"sw":64,"sh":20,"dw":64,"dh":64},{"n":"sco_panel_5_055","t":0,"sx":529,"sy":1476,"sw":64,"sh":20,"dw":64,"dh":64},{"n":"sco_panel_5_056","t":0,"sx":991,"sy":282,"sw":29,"sh":21,"dw":64,"dh":64},{"n":"sco_panel_5_057","t":0,"sx":991,"sy":820,"sw":15,"sh":58,"dx":49,"dy":6,"dw":64,"dh":64},{"n":"sco_panel_5_058","t":0,"sx":727,"sy":651,"sw":64,"sh":57,"dy":7,"dw":64,"dh":64},{"n":"sco_panel_5_059","t":0,"sx":661,"sy":828,"sw":64,"sh":55,"dy":9,"dw":64,"dh":64},{"n":"sco_panel_5_060","t":0,"sx":793,"sy":651,"sw":64,"sh":57,"dy":7,"dw":64,"dh":64},{"n":"sco_panel_5_061","t":0,"sx":529,"sy":651,"sw":64,"sh":58,"dy":6,"dw":64,"dh":64},{"n":"sco_panel_5_062","t":0,"sx":859,"sy":651,"sw":64,"sh":57,"dy":7,"dw":64,"dh":64},{"n":"sco_panel_5_063","t":0,"sx":595,"sy":651,"sw":64,"sh":58,"dy":6,"dw":64,"dh":64},{"n":"sco_panel_5_064","t":0,"sx":727,"sy":710,"sw":64,"sh":57,"dy":7,"dw":64,"dh":64},{"n":"sco_panel_5_065","t":0,"sx":793,"sy":710,"sw":64,"sh":57,"dy":7,"dw":64,"dh":64},{"n":"sco_panel_5_066","t":0,"sx":859,"sy":710,"sw":64,"sh":57,"dy":7,"dw":64,"dh":64},{"n":"sco_panel_5_067","t":0,"sx":331,"sy":1338,"sw":64,"sh":25,"dy":7,"dw":64,"dh":64},{"n":"sco_panel_5_068","t":0,"sx":265,"sy":1363,"sw":64,"sh":25,"dy":7,"dw":64,"dh":64},{"n":"sco_panel_5_069","t":0,"sx":199,"sy":1387,"sw":64,"sh":25,"dy":7,"dw":64,"dh":64},{"n":"sco_panel_5_070","t":0,"sx":397,"sy":1338,"sw":64,"sh":25,"dy":7,"dw":64,"dh":64},{"n":"sco_panel_5_071","t":0,"sx":463,"sy":1139,"sw":64,"sh":31,"dy":7,"dw":64,"dh":64},{"n":"sco_panel_5_072","t":0,"sx":307,"sy":1794,"sw":49,"sh":25,"dy":7,"dw":64,"dh":64},{"n":"sco_panel_5_073","t":0,"sx":991,"sy":946,"sw":11,"sh":2,"dx":53,"dw":64,"dh":64},{"n":"sco_panel_5_074","t":0,"sx":511,"sy":1731,"sw":59,"sh":8,"dw":64,"dh":64},{"n":"sco_panel_5_075","t":0,"sx":436,"sy":1816,"sw":48,"sh":3,"dx":13,"dw":64,"dh":64},{"n":"sco_panel_5_076","t":0,"sx":451,"sy":1675,"sw":62,"sh":3,"dx":1,"dw":64,"dh":64},{"n":"sco_panel_5_077","t":0,"sx":355,"sy":1848,"sw":55,"sh":3,"dx":6,"dw":64,"dh":64},{"n":"sco_panel_5_078","t":0,"sx":191,"sy":1736,"sw":61,"sh":9,"dx":2,"dw":64,"dh":64},{"n":"sco_panel_5_079","t":0,"sx":430,"sy":1756,"sw":50,"sh":3,"dx":14,"dw":64,"dh":64},{"n":"sco_panel_5_080","t":0,"sx":634,"sy":1726,"sw":59,"sh":3,"dw":64,"dh":64},{"n":"sco_panel_5_081","t":0,"sx":307,"sy":1784,"sw":54,"sh":8,"dx":6,"dw":64,"dh":64},{"n":"sco_panel_5_082","t":0,"sx":991,"sy":1,"sw":32,"sh":3,"dw":64,"dh":64},{"n":"sco_panel_5_083","t":0,"sx":986,"sy":1686,"sw":35,"sh":51,"dx":29,"dy":13,"dw":64,"dh":64},{"n":"sco_panel_5_084","t":0,"sx":661,"sy":940,"sw":64,"sh":49,"dy":15,"dw":64,"dh":64},{"n":"sco_panel_5_085","t":0,"sx":727,"sy":940,"sw":64,"sh":46,"dy":18,"dw":64,"dh":64},{"n":"sco_panel_5_086","t":0,"sx":67,"sy":1388,"sw":64,"sh":25,"dy":13,"dw":64,"dh":64},{"n":"sco_panel_5_087","t":0,"sx":921,"sy":1611,"sw":63,"sh":52,"dy":12,"dw":64,"dh":64},{"n":"sco_panel_5_088","t":0,"sx":265,"sy":936,"sw":64,"sh":51,"dy":13,"dw":64,"dh":64},{"n":"sco_panel_5_089","t":0,"sx":331,"sy":936,"sw":64,"sh":51,"dy":13,"dw":64,"dh":64},{"n":"sco_panel_5_090","t":0,"sx":397,"sy":936,"sw":64,"sh":51,"dy":13,"dw":64,"dh":64},{"n":"sco_panel_5_091","t":0,"sx":463,"sy":939,"sw":64,"sh":51,"dy":13,"dw":64,"dh":64},{"n":"sco_panel_5_092","t":0,"sx":1,"sy":937,"sw":64,"sh":51,"dy":13,"dw":64,"dh":64},{"n":"sco_panel_5_093","t":0,"sx":67,"sy":937,"sw":64,"sh":51,"dy":13,"dw":64,"dh":64},{"n":"sco_panel_5_094","t":0,"sx":133,"sy":937,"sw":64,"sh":51,"dy":13,"dw":64,"dh":64},{"n":"sco_panel_5_095","t":0,"sx":921,"sy":1665,"sw":63,"sh":51,"dx":1,"dy":13,"dw":64,"dh":64},{"n":"sco_panel_5_096","t":0,"sx":199,"sy":937,"sw":64,"sh":51,"dy":13,"dw":64,"dh":64},{"n":"sco_panel_5_097","t":0,"sx":1,"sy":1389,"sw":64,"sh":25,"dy":13,"dw":64,"dh":64},{"n":"sco_panel_5_098","t":0,"sx":259,"sy":1690,"sw":61,"sh":46,"dy":18,"dw":64,"dh":64},{"n":"sco_panel_5_099","t":0,"sx":387,"sy":1681,"sw":61,"sh":51,"dx":3,"dy":13,"dw":64,"dh":64},{"n":"sco_panel_5_100","t":0,"sx":265,"sy":989,"sw":64,"sh":51,"dy":13,"dw":64,"dh":64},{"n":"sco_panel_5_101","t":0,"sx":331,"sy":989,"sw":64,"sh":51,"dy":13,"dw":64,"dh":64},{"n":"sco_panel_5_102","t":0,"sx":397,"sy":989,"sw":64,"sh":51,"dy":13,"dw":64,"dh":64},{"n":"sco_panel_5_103","t":0,"sx":312,"sy":1874,"sw":54,"sh":25,"dy":13,"dw":64,"dh":64},{"n":"sco_panel_5_104","t":0,"sx":985,"sy":1739,"sw":38,"sh":64,"dx":26,"dw":64,"dh":64},{"n":"sco_panel_5_105","t":0,"sx":793,"sy":133,"sw":64,"sh":64,"dw":64,"dh":64},{"n":"sco_panel_5_106","t":0,"sx":859,"sy":133,"sw":64,"sh":64,"dw":64,"dh":64},{"n":"sco_panel_5_107","t":0,"sx":925,"sy":133,"sw":64,"sh":64,"dw":64,"dh":64},{"n":"sco_panel_5_108","t":0,"sx":1,"sy":199,"sw":64,"sh":64,"dw":64,"dh":64},{"n":"sco_panel_5_109","t":0,"sx":67,"sy":199,"sw":64,"sh":64,"dw":64,"dh":64},{"n":"sco_panel_5_110","t":0,"sx":133,"sy":199,"sw":64,"sh":64,"dw":64,"dh":64},{"n":"sco_panel_5_111","t":0,"sx":199,"sy":199,"sw":64,"sh":64,"dw":64,"dh":64},{"n":"sco_panel_5_112","t":0,"sx":265,"sy":199,"sw":64,"sh":64,"dw":64,"dh":64},{"n":"sco_panel_5_113","t":0,"sx":331,"sy":199,"sw":64,"sh":64,"dw":64,"dh":64},{"n":"sco_panel_5_114","t":0,"sx":397,"sy":199,"sw":64,"sh":64,"dw":64,"dh":64},{"n":"sco_panel_5_115","t":0,"sx":463,"sy":199,"sw":64,"sh":64,"dw":64,"dh":64},{"n":"sco_panel_5_116","t":0,"sx":529,"sy":199,"sw":64,"sh":64,"dw":64,"dh":64},{"n":"sco_panel_5_117","t":0,"sx":595,"sy":199,"sw":64,"sh":64,"dw":64,"dh":64},{"n":"sco_panel_5_118","t":0,"sx":661,"sy":199,"sw":64,"sh":64,"dw":64,"dh":64},{"n":"sco_panel_5_119","t":0,"sx":727,"sy":199,"sw":64,"sh":64,"dw":64,"dh":64},{"n":"sco_panel_5_120","t":0,"sx":816,"sy":1789,"sw":57,"sh":64,"dw":64,"dh":64},{"n":"sco_panel_5_121","t":0,"sx":661,"sy":1388,"sw":64,"sh":22,"dw":64,"dh":64},{"n":"sco_panel_5_122","t":0,"sx":67,"sy":1223,"sw":64,"sh":27,"dw":64,"dh":64},{"n":"sco_panel_5_123","t":0,"sx":991,"sy":593,"sw":26,"sh":21,"dx":1,"dw":64,"dh":64},{"n":"sco_panel_5_124","t":0,"sx":876,"sy":1771,"sw":35,"sh":11,"dx":29,"dw":64,"dh":64},{"n":"sco_panel_5_125","t":0,"sx":727,"sy":1542,"sw":64,"sh":11,"dw":64,"dh":64},{"n":"sco_panel_5_126","t":0,"sx":595,"sy":1559,"sw":64,"sh":10,"dw":64,"dh":64},{"n":"sco_panel_5_127","t":0,"sx":793,"sy":1543,"sw":64,"sh":11,"dw":64,"dh":64},{"n":"sco_panel_5_128","t":0,"sx":727,"sy":1555,"sw":64,"sh":11,"dw":64,"dh":64},{"n":"sco_panel_5_129","t":0,"sx":634,"sy":1713,"sw":59,"sh":11,"dw":64,"dh":64},{"n":"sco_panel_5_130","t":0,"sx":573,"sy":1722,"sw":59,"sh":11,"dx":2,"dw":64,"dh":64},{"n":"sco_panel_5_131","t":0,"sx":595,"sy":1582,"sw":64,"sh":6,"dw":64,"dh":64},{"n":"sco_panel_5_132","t":0,"sx":131,"sy":1611,"sw":63,"sh":6,"dw":64,"dh":64},{"n":"sco_panel_5_133","t":0,"sx":387,"sy":1673,"sw":62,"sh":6,"dw":64,"dh":64},{"n":"sco_panel_5_134","t":0,"sx":227,"sy":1918,"sw":57,"sh":6,"dx":7,"dw":64,"dh":64},{"n":"sco_panel_5_135","t":0,"sx":450,"sy":1684,"sw":60,"sh":6,"dx":1,"dw":64,"dh":64},{"n":"sco_panel_5_136","t":0,"sx":529,"sy":1586,"sw":64,"sh":6,"dw":64,"dh":64},{"n":"sco_panel_5_137","t":0,"sx":463,"sy":1592,"sw":64,"sh":6,"dw":64,"dh":64},{"n":"sco_panel_5_138","t":0,"sx":925,"sy":1571,"sw":64,"sh":6,"dw":64,"dh":64},{"n":"sco_panel_5_139","t":0,"sx":661,"sy":1557,"sw":64,"sh":11,"dw":64,"dh":64},{"n":"sco_panel_5_140","t":0,"sx":312,"sy":1848,"sw":41,"sh":5,"dw":64,"dh":64},{"n":"sco_panel_6_001","t":0,"sx":196,"sy":1622,"sw":63,"sh":2,"dx":1,"dy":62,"dw":64,"dh":64},{"n":"sco_panel_6_002","t":0,"sx":259,"sy":1685,"sw":62,"sh":3,"dy":61,"dw":64,"dh":64},{"n":"sco_panel_6_003","t":0,"sx":154,"sy":2020,"sw":55,"sh":3,"dx":9,"dy":61,"dw":64,"dh":64},{"n":"sco_panel_6_004","t":0,"sx":595,"sy":1590,"sw":64,"sh":3,"dy":61,"dw":64,"dh":64},{"n":"sco_panel_6_005","t":0,"sx":529,"sy":1594,"sw":64,"sh":3,"dy":61,"dw":64,"dh":64},{"n":"sco_panel_6_006","t":0,"sx":661,"sy":1590,"sw":64,"sh":3,"dy":61,"dw":64,"dh":64},{"n":"sco_panel_6_007","t":0,"sx":727,"sy":1590,"sw":64,"sh":3,"dy":61,"dw":64,"dh":64},{"n":"sco_panel_6_008","t":0,"sx":793,"sy":1594,"sw":64,"sh":3,"dy":61,"dw":64,"dh":64},{"n":"sco_panel_6_009","t":0,"sx":859,"sy":1598,"sw":64,"sh":3,"dy":61,"dw":64,"dh":64},{"n":"sco_panel_6_010","t":0,"sx":925,"sy":1601,"sw":64,"sh":3,"dy":61,"dw":64,"dh":64},{"n":"sco_panel_6_011","t":0,"sx":595,"sy":1595,"sw":64,"sh":3,"dy":61,"dw":64,"dh":64},{"n":"sco_panel_6_012","t":0,"sx":450,"sy":1692,"sw":60,"sh":3,"dy":61,"dw":64,"dh":64},{"n":"sco_panel_6_013","t":0,"sx":451,"sy":1680,"sw":62,"sh":2,"dx":2,"dy":62,"dw":64,"dh":64},{"n":"sco_panel_6_014","t":0,"sx":529,"sy":1599,"sw":64,"sh":3,"dy":61,"dw":64,"dh":64},{"n":"sco_panel_6_015","t":0,"sx":450,"sy":1697,"sw":60,"sh":3,"dy":61,"dw":64,"dh":64},{"n":"sco_panel_6_016","t":0,"sx":163,"sy":1847,"sw":56,"sh":2,"dx":8,"dy":62,"dw":64,"dh":64},{"n":"sco_panel_6_017","t":0,"sx":463,"sy":1600,"sw":64,"sh":3,"dy":61,"dw":64,"dh":64},{"n":"sco_panel_6_018","t":0,"sx":991,"sy":737,"sw":20,"sh":3,"dy":61,"dw":64,"dh":64},{"n":"sco_panel_6_019","t":0,"sx":991,"sy":880,"sw":14,"sh":64,"dx":50,"dw":64,"dh":64},{"n":"sco_panel_6_020","t":0,"sx":925,"sy":1,"sw":64,"sh":64,"dw":64,"dh":64},{"n":"sco_panel_6_021","t":0,"sx":1,"sy":67,"sw":64,"sh":64,"dw":64,"dh":64},{"n":"sco_panel_6_022","t":0,"sx":67,"sy":67,"sw":64,"sh":64,"dw":64,"dh":64},{"n":"sco_panel_6_023","t":0,"sx":133,"sy":67,"sw":64,"sh":64,"dw":64,"dh":64},{"n":"sco_panel_6_024","t":0,"sx":199,"sy":67,"sw":64,"sh":64,"dw":64,"dh":64},{"n":"sco_panel_6_025","t":0,"sx":265,"sy":67,"sw":64,"sh":64,"dw":64,"dh":64},{"n":"sco_panel_6_026","t":0,"sx":331,"sy":67,"sw":64,"sh":64,"dw":64,"dh":64},{"n":"sco_panel_6_027","t":0,"sx":397,"sy":67,"sw":64,"sh":64,"dw":64,"dh":64},{"n":"sco_panel_6_028","t":0,"sx":463,"sy":67,"sw":64,"sh":64,"dw":64,"dh":64},{"n":"sco_panel_6_029","t":0,"sx":529,"sy":67,"sw":64,"sh":64,"dw":64,"dh":64},{"n":"sco_panel_6_030","t":0,"sx":595,"sy":67,"sw":64,"sh":64,"dw":64,"dh":64},{"n":"sco_panel_6_031","t":0,"sx":661,"sy":67,"sw":64,"sh":64,"dw":64,"dh":64},{"n":"sco_panel_6_032","t":0,"sx":727,"sy":67,"sw":64,"sh":64,"dw":64,"dh":64},{"n":"sco_panel_6_033","t":0,"sx":793,"sy":67,"sw":64,"sh":64,"dw":64,"dh":64},{"n":"sco_panel_6_034","t":0,"sx":859,"sy":67,"sw":64,"sh":64,"dw":64,"dh":64},{"n":"sco_panel_6_035","t":0,"sx":925,"sy":67,"sw":64,"sh":64,"dw":64,"dh":64},{"n":"sco_panel_6_036","t":0,"sx":1,"sy":133,"sw":64,"sh":64,"dw":64,"dh":64},{"n":"sco_panel_6_037","t":0,"sx":991,"sy":38,"sw":29,"sh":64,"dw":64,"dh":64},{"n":"sco_panel_6_038","t":0,"sx":1007,"sy":890,"sw":14,"sh":19,"dx":50,"dw":64,"dh":64},{"n":"sco_panel_6_039","t":0,"sx":925,"sy":1483,"sw":64,"sh":20,"dw":64,"dh":64},{"n":"sco_panel_6_040","t":0,"sx":595,"sy":1457,"sw":64,"sh":20,"dw":64,"dh":64},{"n":"sco_panel_6_041","t":0,"sx":925,"sy":1348,"sw":64,"sh":21,"dw":64,"dh":64},{"n":"sco_panel_6_042","t":0,"sx":661,"sy":1457,"sw":64,"sh":20,"dw":64,"dh":64},{"n":"sco_panel_6_043","t":0,"sx":925,"sy":1371,"sw":64,"sh":21,"dw":64,"dh":64},{"n":"sco_panel_6_044","t":0,"sx":859,"sy":1372,"sw":64,"sh":21,"dw":64,"dh":64},{"n":"sco_panel_6_045","t":0,"sx":727,"sy":1478,"sw":64,"sh":20,"dw":64,"dh":64},{"n":"sco_panel_6_046","t":0,"sx":793,"sy":1479,"sw":64,"sh":20,"dw":64,"dh":64},{"n":"sco_panel_6_047","t":0,"sx":859,"sy":1484,"sw":64,"sh":20,"dw":64,"dh":64},{"n":"sco_panel_6_048","t":0,"sx":105,"sy":2025,"sw":57,"sh":20,"dw":64,"dh":64},{"n":"sco_panel_6_049","t":0,"sx":986,"sy":1611,"sw":37,"sh":20,"dx":27,"dw":64,"dh":64},{"n":"sco_panel_6_050","t":0,"sx":925,"sy":1505,"sw":64,"sh":20,"dw":64,"dh":64},{"n":"sco_panel_6_051","t":0,"sx":265,"sy":1469,"sw":64,"sh":20,"dw":64,"dh":64},{"n":"sco_panel_6_052","t":0,"sx":331,"sy":1469,"sw":64,"sh":20,"dw":64,"dh":64},{"n":"sco_panel_6_053","t":0,"sx":397,"sy":1469,"sw":64,"sh":20,"dw":64,"dh":64},{"n":"sco_panel_6_054","t":0,"sx":463,"sy":1474,"sw":64,"sh":20,"dw":64,"dh":64},{"n":"sco_panel_6_055","t":0,"sx":529,"sy":1476,"sw":64,"sh":20,"dw":64,"dh":64},{"n":"sco_panel_6_056","t":0,"sx":991,"sy":282,"sw":29,"sh":21,"dw":64,"dh":64},{"n":"sco_panel_6_057","t":0,"sx":1019,"sy":351,"sw":3,"sh":5,"dx":61,"dy":58,"dw":64,"dh":64},{"n":"sco_panel_6_058","t":0,"sx":463,"sy":590,"sw":64,"sh":59,"dy":5,"dw":64,"dh":64},{"n":"sco_panel_6_059","t":0,"sx":199,"sy":590,"sw":64,"sh":60,"dy":4,"dw":64,"dh":64},{"n":"sco_panel_6_060","t":0,"sx":859,"sy":828,"sw":64,"sh":54,"dy":10,"dw":64,"dh":64},{"n":"sco_panel_6_061","t":0,"sx":925,"sy":829,"sw":64,"sh":54,"dy":10,"dw":64,"dh":64},{"n":"sco_panel_6_062","t":0,"sx":529,"sy":590,"sw":64,"sh":59,"dy":5,"dw":64,"dh":64},{"n":"sco_panel_6_063","t":0,"sx":595,"sy":590,"sw":64,"sh":59,"dy":5,"dw":64,"dh":64},{"n":"sco_panel_6_064","t":0,"sx":265,"sy":590,"sw":64,"sh":60,"dy":4,"dw":64,"dh":64},{"n":"sco_panel_6_065","t":0,"sx":661,"sy":590,"sw":64,"sh":59,"dy":5,"dw":64,"dh":64},{"n":"sco_panel_6_066","t":0,"sx":727,"sy":590,"sw":64,"sh":59,"dy":5,"dw":64,"dh":64},{"n":"sco_panel_6_067","t":0,"sx":793,"sy":590,"sw":64,"sh":59,"dy":5,"dw":64,"dh":64},{"n":"sco_panel_6_068","t":0,"sx":397,"sy":651,"sw":64,"sh":59,"dy":5,"dw":64,"dh":64},{"n":"sco_panel_6_069","t":0,"sx":1,"sy":652,"sw":64,"sh":59,"dy":5,"dw":64,"dh":64},{"n":"sco_panel_6_070","t":0,"sx":67,"sy":652,"sw":64,"sh":59,"dy":5,"dw":64,"dh":64},{"n":"sco_panel_6_071","t":0,"sx":133,"sy":652,"sw":64,"sh":59,"dy":5,"dw":64,"dh":64},{"n":"sco_panel_6_072","t":0,"sx":199,"sy":652,"sw":64,"sh":59,"dy":5,"dw":64,"dh":64},{"n":"sco_panel_6_073","t":0,"sx":265,"sy":652,"sw":64,"sh":59,"dy":5,"dw":64,"dh":64},{"n":"sco_panel_6_074","t":0,"sx":331,"sy":590,"sw":64,"sh":60,"dy":4,"dw":64,"dh":64},{"n":"sco_panel_6_075","t":0,"sx":67,"sy":1192,"sw":64,"sh":29,"dy":5,"dw":64,"dh":64},{"n":"sco_panel_6_076","t":0,"sx":970,"sy":1871,"sw":53,"sh":26,"dy":4,"dw":64,"dh":64},{"n":"sco_panel_6_077","t":0,"sx":793,"sy":199,"sw":64,"sh":64,"dw":64,"dh":64},{"n":"sco_panel_6_078","t":0,"sx":859,"sy":199,"sw":64,"sh":64,"dw":64,"dh":64},{"n":"sco_panel_6_079","t":0,"sx":133,"sy":1388,"sw":64,"sh":25,"dy":39,"dw":64,"dh":64},{"n":"sco_panel_6_080","t":0,"sx":661,"sy":1283,"sw":64,"sh":25,"dy":39,"dw":64,"dh":64},{"n":"sco_panel_6_081","t":0,"sx":595,"sy":1305,"sw":64,"sh":25,"dy":39,"dw":64,"dh":64},{"n":"sco_panel_6_082","t":0,"sx":529,"sy":1324,"sw":64,"sh":25,"dy":39,"dw":64,"dh":64},{"n":"sco_panel_6_083","t":0,"sx":67,"sy":1252,"sw":64,"sh":26,"dy":38,"dw":64,"dh":64},{"n":"sco_panel_6_084","t":0,"sx":790,"sy":1697,"sw":63,"sh":25,"dy":39,"dw":64,"dh":64},{"n":"sco_panel_6_085","t":0,"sx":316,"sy":1739,"sw":59,"sh":20,"dx":5,"dy":44,"dw":64,"dh":64},{"n":"sco_panel_6_086","t":0,"sx":118,"sy":1926,"sw":55,"sh":64,"dw":64,"dh":64},{"n":"sco_panel_6_087","t":0,"sx":463,"sy":1345,"sw":64,"sh":25,"dy":39,"dw":64,"dh":64},{"n":"sco_panel_6_088","t":0,"sx":262,"sy":1615,"sw":63,"sh":20,"dy":44,"dw":64,"dh":64},{"n":"sco_panel_6_089","t":0,"sx":972,"sy":1805,"sw":51,"sh":64,"dw":64,"dh":64},{"n":"sco_panel_6_090","t":0,"sx":1002,"sy":961,"sw":8,"sh":6,"dx":35,"dw":64,"dh":64},{"n":"sco_panel_6_091","t":0,"sx":991,"sy":950,"sw":10,"sh":5,"dx":34,"dw":64,"dh":64},{"n":"sco_panel_6_092","t":0,"sx":1016,"sy":695,"sw":7,"sh":5,"dw":64,"dh":64},{"n":"sco_panel_6_093","t":0,"sx":478,"sy":1768,"sw":33,"sh":9,"dx":31,"dy":55,"dw":64,"dh":64},{"n":"sco_panel_6_094","t":0,"sx":128,"sy":1741,"sw":61,"sh":9,"dx":3,"dy":55,"dw":64,"dh":64},{"n":"sco_panel_6_095","t":0,"sx":859,"sy":1548,"sw":64,"sh":9,"dy":55,"dw":64,"dh":64},{"n":"sco_panel_6_096","t":0,"sx":793,"sy":1556,"sw":64,"sh":9,"dy":55,"dw":64,"dh":64},{"n":"sco_panel_6_097","t":0,"sx":117,"sy":1920,"sw":54,"sh":4,"dy":60,"dw":64,"dh":64},{"n":"sco_panel_6_098","t":0,"sx":925,"sy":1549,"sw":64,"sh":9,"dy":55,"dw":64,"dh":64},{"n":"sco_panel_6_099","t":0,"sx":859,"sy":1559,"sw":64,"sh":9,"dy":55,"dw":64,"dh":64},{"n":"sco_panel_6_100","t":0,"sx":129,"sy":1691,"sw":62,"sh":9,"dx":2,"dy":55,"dw":64,"dh":64},{"n":"sco_panel_6_101","t":0,"sx":793,"sy":1567,"sw":64,"sh":9,"dy":55,"dw":64,"dh":64},{"n":"sco_panel_6_102","t":0,"sx":727,"sy":1568,"sw":64,"sh":9,"dy":55,"dw":64,"dh":64},{"n":"sco_panel_6_103","t":0,"sx":661,"sy":1570,"sw":64,"sh":9,"dy":55,"dw":64,"dh":64},{"n":"sco_panel_6_104","t":0,"sx":991,"sy":666,"sw":24,"sh":9,"dy":55,"dw":64,"dh":64},{"n":"sco_panel_6_105","t":0,"sx":875,"sy":1793,"sw":34,"sh":51,"dx":30,"dw":64,"dh":64},{"n":"sco_panel_6_106","t":0,"sx":1,"sy":990,"sw":64,"sh":51,"dw":64,"dh":64},{"n":"sco_panel_6_107","t":0,"sx":529,"sy":770,"sw":64,"sh":56,"dw":64,"dh":64},{"n":"sco_panel_6_108","t":0,"sx":67,"sy":990,"sw":64,"sh":51,"dw":64,"dh":64},{"n":"sco_panel_6_109","t":0,"sx":133,"sy":990,"sw":64,"sh":51,"dw":64,"dh":64},{"n":"sco_panel_6_110","t":0,"sx":199,"sy":990,"sw":64,"sh":51,"dw":64,"dh":64},{"n":"sco_panel_6_111","t":0,"sx":595,"sy":940,"sw":64,"sh":50,"dw":64,"dh":64},{"n":"sco_panel_6_112","t":0,"sx":529,"sy":940,"sw":64,"sh":51,"dw":64,"dh":64},{"n":"sco_panel_6_113","t":0,"sx":595,"sy":770,"sw":64,"sh":56,"dw":64,"dh":64},{"n":"sco_panel_6_114","t":0,"sx":463,"sy":992,"sw":64,"sh":51,"dw":64,"dh":64},{"n":"sco_panel_6_115","t":0,"sx":265,"sy":1042,"sw":64,"sh":51,"dw":64,"dh":64},{"n":"sco_panel_6_116","t":0,"sx":1,"sy":1874,"sw":56,"sh":50,"dw":64,"dh":64},{"n":"sco_panel_6_117","t":0,"sx":875,"sy":1846,"sw":34,"sh":26,"dx":30,"dy":33,"dw":64,"dh":64},{"n":"sco_panel_6_118","t":0,"sx":595,"sy":1359,"sw":64,"sh":24,"dy":34,"dw":64,"dh":64},{"n":"sco_panel_6_119","t":0,"sx":727,"sy":1283,"sw":64,"sh":25,"dy":34,"dw":64,"dh":64},{"n":"sco_panel_6_120","t":0,"sx":512,"sy":1701,"sw":59,"sh":28,"dy":36,"dw":64,"dh":64},{"n":"sco_panel_6_121","t":0,"sx":1,"sy":1761,"sw":60,"sh":25,"dx":4,"dy":39,"dw":64,"dh":64},{"n":"sco_panel_6_122","t":0,"sx":1,"sy":1788,"sw":60,"sh":25,"dy":34,"dw":64,"dh":64},{"n":"sco_panel_6_123","t":0,"sx":450,"sy":1702,"sw":59,"sh":25,"dx":5,"dy":34,"dw":64,"dh":64},{"n":"sco_panel_6_124","t":0,"sx":855,"sy":1700,"sw":63,"sh":25,"dy":34,"dw":64,"dh":64},{"n":"sco_panel_6_125","t":0,"sx":793,"sy":1287,"sw":64,"sh":25,"dy":34,"dw":64,"dh":64},{"n":"sco_panel_6_126","t":0,"sx":920,"sy":1718,"sw":63,"sh":25,"dx":1,"dy":34,"dw":64,"dh":64},{"n":"sco_panel_6_127","t":0,"sx":331,"sy":1365,"sw":64,"sh":25,"dy":34,"dw":64,"dh":64},{"n":"sco_panel_6_128","t":0,"sx":854,"sy":1727,"sw":58,"sh":20,"dy":39,"dw":64,"dh":64},{"n":"sco_panel_6_129","t":0,"sx":401,"sy":1794,"sw":33,"sh":25,"dx":31,"dy":5,"dw":64,"dh":64},{"n":"sco_panel_6_130","t":0,"sx":327,"sy":1631,"sw":63,"sh":20,"dx":1,"dy":10,"dw":64,"dh":64},{"n":"sco_panel_6_131","t":0,"sx":265,"sy":1390,"sw":64,"sh":25,"dy":5,"dw":64,"dh":64},{"n":"sco_panel_6_132","t":0,"sx":199,"sy":1414,"sw":64,"sh":25,"dy":5,"dw":64,"dh":64},{"n":"sco_panel_6_133","t":0,"sx":397,"sy":1165,"sw":64,"sh":31,"dy":5,"dw":64,"dh":64},{"n":"sco_panel_6_134","t":0,"sx":397,"sy":1365,"sw":64,"sh":25,"dy":5,"dw":64,"dh":64},{"n":"sco_panel_6_135","t":0,"sx":67,"sy":1415,"sw":64,"sh":25,"dy":5,"dw":64,"dh":64},{"n":"sco_panel_6_136","t":0,"sx":436,"sy":1794,"sw":47,"sh":20,"dy":10,"dw":64,"dh":64},{"n":"sco_panel_7_001","t":0,"sx":1007,"sy":937,"sw":13,"sh":3,"dx":51,"dy":61,"dw":64,"dh":64},{"n":"sco_panel_7_002","t":0,"sx":661,"sy":1595,"sw":64,"sh":3,"dy":61,"dw":64,"dh":64},{"n":"sco_panel_7_003","t":0,"sx":463,"sy":1605,"sw":64,"sh":2,"dy":62,"dw":64,"dh":64},{"n":"sco_panel_7_004","t":0,"sx":727,"sy":1595,"sw":64,"sh":3,"dy":61,"dw":64,"dh":64},{"n":"sco_panel_7_005","t":0,"sx":793,"sy":1599,"sw":64,"sh":3,"dy":61,"dw":64,"dh":64},{"n":"sco_panel_7_006","t":0,"sx":859,"sy":1603,"sw":64,"sh":3,"dy":61,"dw":64,"dh":64},{"n":"sco_panel_7_007","t":0,"sx":925,"sy":1606,"sw":64,"sh":3,"dy":61,"dw":64,"dh":64},{"n":"sco_panel_7_008","t":0,"sx":595,"sy":1600,"sw":64,"sh":3,"dy":61,"dw":64,"dh":64},{"n":"sco_panel_7_009","t":0,"sx":164,"sy":2025,"sw":45,"sh":3,"dy":61,"dw":64,"dh":64},{"n":"sco_panel_7_010","t":0,"sx":270,"sy":1851,"sw":40,"sh":64,"dx":24,"dw":64,"dh":64},{"n":"sco_panel_7_011","t":0,"sx":925,"sy":199,"sw":64,"sh":64,"dw":64,"dh":64},{"n":"sco_panel_7_012","t":0,"sx":1,"sy":265,"sw":64,"sh":64,"dw":64,"dh":64},{"n":"sco_panel_7_013","t":0,"sx":67,"sy":265,"sw":64,"sh":64,"dw":64,"dh":64},{"n":"sco_panel_7_014","t":0,"sx":133,"sy":265,"sw":64,"sh":64,"dw":64,"dh":64},{"n":"sco_panel_7_015","t":0,"sx":199,"sy":265,"sw":64,"sh":64,"dw":64,"dh":64},{"n":"sco_panel_7_016","t":0,"sx":265,"sy":265,"sw":64,"sh":64,"dw":64,"dh":64},{"n":"sco_panel_7_017","t":0,"sx":331,"sy":265,"sw":64,"sh":64,"dw":64,"dh":64},{"n":"sco_panel_7_018","t":0,"sx":756,"sy":1728,"sw":58,"sh":64,"dw":64,"dh":64},{"n":"sco_panel_7_019","t":0,"sx":986,"sy":1664,"sw":36,"sh":20,"dx":28,"dw":64,"dh":64},{"n":"sco_panel_7_020","t":0,"sx":925,"sy":1527,"sw":64,"sh":20,"dw":64,"dh":64},{"n":"sco_panel_7_021","t":0,"sx":265,"sy":1491,"sw":64,"sh":20,"dw":64,"dh":64},{"n":"sco_panel_7_022","t":0,"sx":199,"sy":1493,"sw":64,"sh":20,"dw":64,"dh":64},{"n":"sco_panel_7_023","t":0,"sx":793,"sy":1389,"sw":64,"sh":21,"dw":64,"dh":64},{"n":"sco_panel_7_024","t":0,"sx":727,"sy":1411,"sw":64,"sh":21,"dw":64,"dh":64},{"n":"sco_panel_7_025","t":0,"sx":661,"sy":1412,"sw":64,"sh":21,"dw":64,"dh":64},{"n":"sco_panel_7_026","t":0,"sx":595,"sy":1434,"sw":64,"sh":21,"dw":64,"dh":64},{"n":"sco_panel_7_027","t":0,"sx":991,"sy":798,"sw":16,"sh":20,"dw":64,"dh":64},{"n":"sco_panel_7_028","t":0,"sx":991,"sy":312,"sw":28,"sh":28,"dx":36,"dy":36,"dw":64,"dh":64},{"n":"sco_panel_7_029","t":0,"sx":595,"sy":1410,"sw":64,"sh":22,"dy":42,"dw":64,"dh":64},{"n":"sco_panel_7_030","t":0,"sx":67,"sy":1494,"sw":64,"sh":20,"dy":42,"dw":64,"dh":64},{"n":"sco_panel_7_031","t":0,"sx":1,"sy":1224,"sw":64,"sh":27,"dy":37,"dw":64,"dh":64},{"n":"sco_panel_7_032","t":0,"sx":1,"sy":1416,"sw":64,"sh":25,"dy":37,"dw":64,"dh":64},{"n":"sco_panel_7_033","t":0,"sx":133,"sy":1223,"sw":64,"sh":27,"dy":37,"dw":64,"dh":64},{"n":"sco_panel_7_034","t":0,"sx":199,"sy":1223,"sw":64,"sh":27,"dy":37,"dw":64,"dh":64},{"n":"sco_panel_7_035","t":0,"sx":133,"sy":1469,"sw":64,"sh":23,"dy":39,"dw":64,"dh":64},{"n":"sco_panel_7_036","t":0,"sx":323,"sy":1653,"sw":62,"sh":25,"dy":37,"dw":64,"dh":64},{"n":"sco_panel_7_037","t":0,"sx":572,"sy":1735,"sw":58,"sh":25,"dx":6,"dy":37,"dw":64,"dh":64},{"n":"sco_panel_7_038","t":0,"sx":265,"sy":1226,"sw":64,"sh":27,"dy":37,"dw":64,"dh":64},{"n":"sco_panel_7_039","t":0,"sx":529,"sy":1429,"sw":64,"sh":22,"dy":42,"dw":64,"dh":64},{"n":"sco_panel_7_040","t":0,"sx":991,"sy":710,"sw":21,"sh":19,"dy":42,"dw":64,"dh":64},{"n":"sco_panel_7_041","t":0,"sx":991,"sy":104,"sw":29,"sh":64,"dx":35,"dw":64,"dh":64},{"n":"sco_panel_7_042","t":0,"sx":397,"sy":1607,"sw":63,"sh":64,"dw":64,"dh":64},{"n":"sco_panel_7_043","t":0,"sx":661,"sy":770,"sw":64,"sh":56,"dy":8,"dw":64,"dh":64},{"n":"sco_panel_7_044","t":0,"sx":397,"sy":265,"sw":64,"sh":64,"dw":64,"dh":64},{"n":"sco_panel_7_045","t":0,"sx":133,"sy":1415,"sw":64,"sh":25,"dy":9,"dw":64,"dh":64},{"n":"sco_panel_7_046","t":0,"sx":331,"sy":1095,"sw":64,"sh":34,"dw":64,"dh":64},{"n":"sco_panel_7_047","t":0,"sx":163,"sy":1814,"sw":56,"sh":31,"dy":9,"dw":64,"dh":64},{"n":"sco_panel_7_048","t":0,"sx":859,"sy":1323,"sw":64,"sh":23,"dy":11,"dw":64,"dh":64},{"n":"sco_panel_7_049","t":0,"sx":133,"sy":1128,"sw":64,"sh":30,"dy":9,"dw":64,"dh":64},{"n":"sco_panel_7_050","t":0,"sx":1,"sy":1495,"sw":64,"sh":20,"dy":14,"dw":64,"dh":64},{"n":"sco_panel_7_051","t":0,"sx":397,"sy":1095,"sw":64,"sh":34,"dw":64,"dh":64},{"n":"sco_panel_7_052","t":0,"sx":331,"sy":1131,"sw":64,"sh":34,"dw":64,"dh":64},{"n":"sco_panel_7_053","t":0,"sx":199,"sy":1128,"sw":64,"sh":30,"dy":9,"dw":64,"dh":64},{"n":"sco_panel_7_054","t":0,"sx":265,"sy":1132,"sw":64,"sh":30,"dy":9,"dw":64,"dh":64},{"n":"sco_panel_7_055","t":0,"sx":450,"sy":1729,"sw":59,"sh":25,"dy":9,"dw":64,"dh":64},{"n":"sco_panel_7_056","t":0,"sx":511,"sy":1741,"sw":58,"sh":25,"dy":9,"dw":64,"dh":64},{"n":"sco_panel_7_057","t":0,"sx":527,"sy":1674,"sw":63,"sh":25,"dx":1,"dy":9,"dw":64,"dh":64},{"n":"sco_panel_7_058","t":0,"sx":1,"sy":1685,"sw":62,"sh":30,"dy":9,"dw":64,"dh":64},{"n":"sco_panel_7_059","t":0,"sx":632,"sy":1758,"sw":58,"sh":25,"dx":6,"dy":9,"dw":64,"dh":64},{"n":"sco_panel_7_060","t":0,"sx":1012,"sy":751,"sw":11,"sh":24,"dy":9,"dw":64,"dh":64},{"n":"sco_panel_7_061","t":0,"sx":991,"sy":305,"sw":29,"sh":5,"dx":35,"dw":64,"dh":64},{"n":"sco_panel_7_062","t":0,"sx":128,"sy":1729,"sw":61,"sh":10,"dx":2,"dw":64,"dh":64},{"n":"sco_panel_7_063","t":0,"sx":463,"sy":265,"sw":64,"sh":64,"dw":64,"dh":64},{"n":"sco_panel_7_064","t":0,"sx":529,"sy":265,"sw":64,"sh":64,"dw":64,"dh":64},{"n":"sco_panel_7_065","t":0,"sx":463,"sy":1045,"sw":64,"sh":45,"dy":19,"dw":64,"dh":64},{"n":"sco_panel_7_066","t":0,"sx":925,"sy":995,"sw":64,"sh":45,"dy":19,"dw":64,"dh":64},{"n":"sco_panel_7_067","t":0,"sx":793,"sy":940,"sw":64,"sh":46,"dy":18,"dw":64,"dh":64},{"n":"sco_panel_7_068","t":0,"sx":859,"sy":1041,"sw":64,"sh":45,"dy":19,"dw":64,"dh":64},{"n":"sco_panel_7_069","t":0,"sx":793,"sy":1082,"sw":64,"sh":45,"dy":19,"dw":64,"dh":64},{"n":"sco_panel_7_070","t":0,"sx":727,"sy":988,"sw":64,"sh":46,"dy":18,"dw":64,"dh":64},{"n":"sco_panel_7_071","t":0,"sx":793,"sy":1217,"sw":64,"sh":40,"dy":24,"dw":64,"dh":64},{"n":"sco_panel_7_072","t":0,"sx":727,"sy":1083,"sw":64,"sh":45,"dy":19,"dw":64,"dh":64},{"n":"sco_panel_7_073","t":0,"sx":661,"sy":1085,"sw":64,"sh":45,"dy":19,"dw":64,"dh":64},{"n":"sco_panel_7_074","t":0,"sx":595,"sy":1086,"sw":64,"sh":45,"dy":19,"dw":64,"dh":64},{"n":"sco_panel_7_075","t":0,"sx":529,"sy":1087,"sw":64,"sh":45,"dy":19,"dw":64,"dh":64},{"n":"sco_panel_7_076","t":0,"sx":463,"sy":1092,"sw":64,"sh":45,"dy":19,"dw":64,"dh":64},{"n":"sco_panel_7_077","t":0,"sx":67,"sy":1160,"sw":64,"sh":30,"dy":19,"dw":64,"dh":64},{"n":"sco_panel_7_078","t":0,"sx":529,"sy":1378,"sw":64,"sh":24,"dy":19,"dw":64,"dh":64},{"n":"sco_panel_7_079","t":0,"sx":914,"sy":1745,"sw":58,"sh":20,"dy":24,"dw":64,"dh":64},{"n":"sco_panel_7_080","t":0,"sx":991,"sy":481,"sw":26,"sh":56,"dx":38,"dw":64,"dh":64},{"n":"sco_panel_7_081","t":0,"sx":1,"sy":713,"sw":64,"sh":56,"dw":64,"dh":64},{"n":"sco_panel_7_082","t":0,"sx":67,"sy":713,"sw":64,"sh":56,"dw":64,"dh":64},{"n":"sco_panel_7_083","t":0,"sx":133,"sy":713,"sw":64,"sh":56,"dw":64,"dh":64},{"n":"sco_panel_7_084","t":0,"sx":727,"sy":828,"sw":64,"sh":55,"dw":64,"dh":64},{"n":"sco_panel_7_085","t":0,"sx":199,"sy":713,"sw":64,"sh":56,"dw":64,"dh":64},{"n":"sco_panel_7_086","t":0,"sx":265,"sy":713,"sw":64,"sh":56,"dw":64,"dh":64},{"n":"sco_panel_7_087","t":0,"sx":1,"sy":771,"sw":64,"sh":56,"dw":64,"dh":64},{"n":"sco_panel_7_088","t":0,"sx":859,"sy":462,"sw":64,"sh":61,"dw":64,"dh":64},{"n":"sco_panel_7_089","t":0,"sx":925,"sy":462,"sw":64,"sh":61,"dw":64,"dh":64},{"n":"sco_panel_7_090","t":0,"sx":67,"sy":771,"sw":64,"sh":56,"dw":64,"dh":64},{"n":"sco_panel_7_091","t":0,"sx":133,"sy":771,"sw":64,"sh":56,"dw":64,"dh":64},{"n":"sco_panel_7_092","t":0,"sx":199,"sy":771,"sw":64,"sh":56,"dw":64,"dh":64},{"n":"sco_panel_7_093","t":0,"sx":265,"sy":771,"sw":64,"sh":56,"dw":64,"dh":64},{"n":"sco_panel_7_094","t":0,"sx":1,"sy":1161,"sw":64,"sh":30,"dy":31,"dw":64,"dh":64},{"n":"sco_panel_7_095","t":0,"sx":463,"sy":1399,"sw":64,"sh":24,"dy":31,"dw":64,"dh":64},{"n":"sco_panel_7_096","t":0,"sx":854,"sy":1749,"sw":58,"sh":20,"dy":36,"dw":64,"dh":64},{"n":"sco_panel_7_097","t":0,"sx":991,"sy":417,"sw":26,"sh":62,"dx":38,"dy":2,"dw":64,"dh":64},{"n":"sco_panel_7_098","t":0,"sx":859,"sy":525,"sw":64,"sh":61,"dy":3,"dw":64,"dh":64},{"n":"sco_panel_7_099","t":0,"sx":925,"sy":525,"sw":64,"sh":61,"dy":3,"dw":64,"dh":64},{"n":"sco_panel_7_100","t":0,"sx":463,"sy":527,"sw":64,"sh":61,"dy":3,"dw":64,"dh":64},{"n":"sco_panel_7_101","t":0,"sx":331,"sy":771,"sw":64,"sh":56,"dy":8,"dw":64,"dh":64},{"n":"sco_panel_7_102","t":0,"sx":529,"sy":527,"sw":64,"sh":61,"dy":3,"dw":64,"dh":64},{"n":"sco_panel_7_103","t":0,"sx":595,"sy":527,"sw":64,"sh":61,"dy":3,"dw":64,"dh":64},{"n":"sco_panel_7_104","t":0,"sx":661,"sy":527,"sw":64,"sh":61,"dy":3,"dw":64,"dh":64},{"n":"sco_panel_7_105","t":0,"sx":727,"sy":527,"sw":64,"sh":61,"dy":3,"dw":64,"dh":64},{"n":"sco_panel_7_106","t":0,"sx":793,"sy":527,"sw":64,"sh":61,"dy":3,"dw":64,"dh":64},{"n":"sco_panel_7_107","t":0,"sx":397,"sy":771,"sw":64,"sh":56,"dy":8,"dw":64,"dh":64},{"n":"sco_panel_7_108","t":0,"sx":859,"sy":588,"sw":64,"sh":61,"dy":3,"dw":64,"dh":64},{"n":"sco_panel_7_109","t":0,"sx":463,"sy":828,"sw":64,"sh":56,"dy":8,"dw":64,"dh":64},{"n":"sco_panel_7_110","t":0,"sx":529,"sy":1453,"sw":64,"sh":21,"dy":43,"dw":64,"dh":64},{"n":"sco_panel_7_111","t":0,"sx":925,"sy":1394,"sw":64,"sh":21,"dy":43,"dw":64,"dh":64},{"n":"sco_panel_7_112","t":0,"sx":859,"sy":1395,"sw":64,"sh":21,"dy":43,"dw":64,"dh":64},{"n":"sco_panel_7_113","t":0,"sx":125,"sy":1796,"sw":57,"sh":16,"dy":48,"dw":64,"dh":64},{"n":"sco_panel_7_114","t":0,"sx":991,"sy":351,"sw":26,"sh":64,"dx":38,"dw":64,"dh":64},{"n":"sco_panel_7_115","t":0,"sx":595,"sy":265,"sw":64,"sh":64,"dw":64,"dh":64},{"n":"sco_panel_7_116","t":0,"sx":661,"sy":265,"sw":64,"sh":64,"dw":64,"dh":64},{"n":"sco_panel_7_117","t":0,"sx":727,"sy":265,"sw":64,"sh":64,"dw":64,"dh":64},{"n":"sco_panel_7_118","t":0,"sx":661,"sy":1600,"sw":63,"sh":64,"dx":1,"dw":64,"dh":64},{"n":"sco_panel_7_119","t":0,"sx":793,"sy":265,"sw":64,"sh":64,"dw":64,"dh":64},{"n":"sco_panel_7_120","t":0,"sx":859,"sy":265,"sw":64,"sh":64,"dw":64,"dh":64},{"n":"sco_panel_7_121","t":0,"sx":925,"sy":265,"sw":64,"sh":64,"dw":64,"dh":64},{"n":"sco_panel_7_122","t":0,"sx":1,"sy":331,"sw":64,"sh":64,"dw":64,"dh":64},{"n":"sco_panel_7_123","t":0,"sx":595,"sy":1605,"sw":63,"sh":64,"dw":64,"dh":64},{"n":"sco_panel_7_124","t":0,"sx":131,"sy":1625,"sw":62,"sh":64,"dx":2,"dw":64,"dh":64},{"n":"sco_panel_7_125","t":0,"sx":67,"sy":331,"sw":64,"sh":64,"dw":64,"dh":64},{"n":"sco_panel_7_126","t":0,"sx":133,"sy":331,"sw":64,"sh":64,"dw":64,"dh":64},{"n":"sco_panel_7_127","t":0,"sx":199,"sy":331,"sw":64,"sh":64,"dw":64,"dh":64},{"n":"sco_panel_7_128","t":0,"sx":265,"sy":331,"sw":64,"sh":64,"dw":64,"dh":64},{"n":"sco_panel_7_129","t":0,"sx":331,"sy":331,"sw":64,"sh":64,"dw":64,"dh":64},{"n":"sco_panel_7_130","t":0,"sx":529,"sy":1608,"sw":63,"sh":64,"dw":64,"dh":64},{"n":"sco_panel_7_131","t":0,"sx":991,"sy":731,"sw":21,"sh":4,"dx":2,"dy":60,"dw":64,"dh":64},{"n":"sco_panel_7_132","t":0,"sx":991,"sy":539,"sw":26,"sh":52,"dx":38,"dw":64,"dh":64},{"n":"sco_panel_7_133","t":0,"sx":1,"sy":829,"sw":64,"sh":52,"dw":64,"dh":64},{"n":"sco_panel_7_134","t":0,"sx":67,"sy":829,"sw":64,"sh":52,"dw":64,"dh":64},{"n":"sco_panel_7_135","t":0,"sx":925,"sy":712,"sw":64,"sh":57,"dw":64,"dh":64},{"n":"sco_panel_7_136","t":0,"sx":133,"sy":829,"sw":64,"sh":52,"dw":64,"dh":64},{"n":"sco_panel_7_137","t":0,"sx":463,"sy":711,"sw":64,"sh":57,"dw":64,"dh":64},{"n":"sco_panel_7_138","t":0,"sx":199,"sy":829,"sw":64,"sh":52,"dw":64,"dh":64},{"n":"sco_panel_7_139","t":0,"sx":265,"sy":829,"sw":64,"sh":52,"dw":64,"dh":64},{"n":"sco_panel_7_140","t":0,"sx":331,"sy":829,"sw":64,"sh":52,"dw":64,"dh":64},{"n":"sco_panel_7_141","t":0,"sx":397,"sy":829,"sw":64,"sh":52,"dw":64,"dh":64},{"n":"sco_panel_7_142","t":0,"sx":331,"sy":712,"sw":64,"sh":57,"dw":64,"dh":64},{"n":"sco_panel_7_143","t":0,"sx":1,"sy":883,"sw":64,"sh":52,"dw":64,"dh":64},{"n":"sco_panel_7_144","t":0,"sx":323,"sy":1686,"sw":61,"sh":51,"dw":64,"dh":64},{"n":"sco_panel_7_145","t":0,"sx":573,"sy":1704,"sw":59,"sh":16,"dx":5,"dw":64,"dh":64},{"n":"sco_panel_7_146","t":0,"sx":793,"sy":1412,"sw":64,"sh":21,"dw":64,"dh":64},{"n":"sco_panel_7_147","t":0,"sx":1,"sy":1738,"sw":61,"sh":16,"dw":64,"dh":64},{"n":"sco_panel_7_148","t":0,"sx":816,"sy":1771,"sw":58,"sh":16,"dx":6,"dw":64,"dh":64},{"n":"sco_panel_7_149","t":0,"sx":991,"sy":648,"sw":24,"sh":16,"dw":64,"dh":64},{"n":"sco_panel_7_150","t":0,"sx":991,"sy":170,"sw":29,"sh":57,"dx":35,"dy":7,"dw":64,"dh":64},{"n":"sco_panel_7_151","t":0,"sx":661,"sy":651,"sw":64,"sh":58,"dy":6,"dw":64,"dh":64},{"n":"sco_panel_7_152","t":0,"sx":67,"sy":883,"sw":64,"sh":52,"dy":12,"dw":64,"dh":64},{"n":"sco_panel_7_153","t":0,"sx":397,"sy":712,"sw":64,"sh":57,"dy":7,"dw":64,"dh":64},{"n":"sco_panel_7_154","t":0,"sx":529,"sy":711,"sw":64,"sh":57,"dy":7,"dw":64,"dh":64},{"n":"sco_panel_7_155","t":0,"sx":595,"sy":711,"sw":64,"sh":57,"dy":7,"dw":64,"dh":64},{"n":"sco_panel_7_156","t":0,"sx":661,"sy":711,"sw":64,"sh":57,"dy":7,"dw":64,"dh":64},{"n":"sco_panel_7_157","t":0,"sx":793,"sy":828,"sw":64,"sh":55,"dy":9,"dw":64,"dh":64},{"n":"sco_panel_7_158","t":0,"sx":727,"sy":769,"sw":64,"sh":57,"dy":7,"dw":64,"dh":64},{"n":"sco_panel_7_159","t":0,"sx":133,"sy":883,"sw":64,"sh":52,"dy":12,"dw":64,"dh":64},{"n":"sco_panel_7_160","t":0,"sx":793,"sy":769,"sw":64,"sh":57,"dy":7,"dw":64,"dh":64},{"n":"sco_panel_7_161","t":0,"sx":199,"sy":883,"sw":64,"sh":52,"dy":12,"dw":64,"dh":64},{"n":"sco_panel_7_162","t":0,"sx":1,"sy":1193,"sw":64,"sh":29,"dy":7,"dw":64,"dh":64},{"n":"sco_panel_7_163","t":0,"sx":661,"sy":1310,"sw":64,"sh":25,"dy":12,"dw":64,"dh":64},{"n":"sco_panel_7_164","t":0,"sx":331,"sy":1228,"sw":64,"sh":27,"dy":7,"dw":64,"dh":64},{"n":"sco_panel_7_165","t":0,"sx":595,"sy":1332,"sw":64,"sh":25,"dy":7,"dw":64,"dh":64},{"n":"sco_panel_7_166","t":0,"sx":594,"sy":1671,"sw":63,"sh":31,"dy":7,"dw":64,"dh":64},{"n":"sco_panel_7_167","t":0,"sx":529,"sy":1351,"sw":64,"sh":25,"dy":7,"dw":64,"dh":64},{"n":"sco_panel_7_168","t":0,"sx":463,"sy":1372,"sw":64,"sh":25,"dy":7,"dw":64,"dh":64},{"n":"sco_panel_7_169","t":0,"sx":793,"sy":1340,"sw":64,"sh":23,"dy":9,"dw":64,"dh":64},{"n":"sco_panel_7_170","t":0,"sx":991,"sy":229,"sw":29,"sh":25,"dy":7,"dw":64,"dh":64},{"n":"sco_panel_7_171","t":0,"sx":991,"sy":637,"sw":26,"sh":9,"dx":37,"dw":64,"dh":64},{"n":"sco_panel_7_172","t":0,"sx":64,"sy":1751,"sw":61,"sh":4,"dx":3,"dw":64,"dh":64},{"n":"sco_panel_7_173","t":0,"sx":925,"sy":1579,"sw":64,"sh":4,"dw":64,"dh":64},{"n":"sco_panel_7_174","t":0,"sx":859,"sy":1581,"sw":64,"sh":4,"dw":64,"dh":64},{"n":"sco_panel_7_175","t":0,"sx":925,"sy":1585,"sw":64,"sh":4,"dw":64,"dh":64},{"n":"sco_panel_7_176","t":0,"sx":859,"sy":1587,"sw":64,"sh":4,"dw":64,"dh":64},{"n":"sco_panel_7_177","t":0,"sx":323,"sy":1680,"sw":62,"sh":4,"dw":64,"dh":64},{"n":"sco_panel_7_178","t":0,"sx":59,"sy":1920,"sw":56,"sh":4,"dx":8,"dw":64,"dh":64},{"n":"sco_panel_7_179","t":0,"sx":131,"sy":1619,"sw":63,"sh":4,"dw":64,"dh":64},{"n":"sco_panel_7_180","t":0,"sx":173,"sy":1920,"sw":52,"sh":4,"dx":2,"dw":64,"dh":64},{"n":"sco_panel_7_181","t":0,"sx":595,"sy":1571,"sw":64,"sh":9,"dw":64,"dh":64},{"n":"sco_panel_7_182","t":0,"sx":66,"sy":1622,"sw":63,"sh":4,"dw":64,"dh":64},{"n":"sco_panel_8_001","t":0,"sx":312,"sy":1901,"sw":40,"sh":14,"dx":13,"dy":50,"dw":64,"dh":64},{"n":"sco_panel_8_002","t":0,"sx":143,"sy":1855,"sw":39,"sh":63,"dx":25,"dy":1,"dw":64,"dh":64},{"n":"sco_panel_8_003","t":0,"sx":265,"sy":463,"sw":64,"sh":63,"dy":1,"dw":64,"dh":64},{"n":"sco_panel_8_004","t":0,"sx":331,"sy":463,"sw":64,"sh":63,"dy":1,"dw":64,"dh":64},{"n":"sco_panel_8_005","t":0,"sx":397,"sy":463,"sw":64,"sh":63,"dy":1,"dw":64,"dh":64},{"n":"sco_panel_8_006","t":0,"sx":529,"sy":462,"sw":64,"sh":63,"dy":1,"dw":64,"dh":64},{"n":"sco_panel_8_007","t":0,"sx":595,"sy":462,"sw":64,"sh":63,"dy":1,"dw":64,"dh":64},{"n":"sco_panel_8_008","t":0,"sx":661,"sy":462,"sw":64,"sh":63,"dy":1,"dw":64,"dh":64},{"n":"sco_panel_8_009","t":0,"sx":727,"sy":462,"sw":64,"sh":63,"dy":1,"dw":64,"dh":64},{"n":"sco_panel_8_010","t":0,"sx":397,"sy":331,"sw":64,"sh":64,"dw":64,"dh":64},{"n":"sco_panel_8_011","t":0,"sx":793,"sy":462,"sw":64,"sh":63,"dy":1,"dw":64,"dh":64},{"n":"sco_panel_8_012","t":0,"sx":913,"sy":1788,"sw":57,"sh":64,"dw":64,"dh":64},{"n":"sco_panel_8_013","t":0,"sx":59,"sy":1900,"sw":38,"sh":17,"dx":26,"dw":64,"dh":64},{"n":"sco_panel_8_014","t":0,"sx":529,"sy":1538,"sw":64,"sh":17,"dw":64,"dh":64},{"n":"sco_panel_8_015","t":0,"sx":331,"sy":1552,"sw":64,"sh":17,"dw":64,"dh":64},{"n":"sco_panel_8_016","t":0,"sx":265,"sy":1553,"sw":64,"sh":17,"dw":64,"dh":64},{"n":"sco_panel_8_017","t":0,"sx":199,"sy":1554,"sw":64,"sh":17,"dw":64,"dh":64},{"n":"sco_panel_8_018","t":0,"sx":397,"sy":1552,"sw":64,"sh":17,"dw":64,"dh":64},{"n":"sco_panel_8_019","t":0,"sx":463,"sy":1555,"sw":64,"sh":17,"dw":64,"dh":64},{"n":"sco_panel_8_020","t":0,"sx":331,"sy":1571,"sw":64,"sh":17,"dw":64,"dh":64},{"n":"sco_panel_8_021","t":0,"sx":265,"sy":1572,"sw":64,"sh":17,"dw":64,"dh":64},{"n":"sco_panel_8_022","t":0,"sx":1,"sy":1556,"sw":64,"sh":16,"dw":64,"dh":64},{"n":"sco_panel_8_023","t":0,"sx":565,"sy":1804,"sw":56,"sh":16,"dw":64,"dh":64},{"n":"sco_panel_8_024","t":0,"sx":403,"sy":1821,"sw":51,"sh":23,"dx":13,"dy":41,"dw":64,"dh":64},{"n":"sco_panel_8_025","t":0,"sx":925,"sy":1323,"sw":64,"sh":23,"dy":41,"dw":64,"dh":64},{"n":"sco_panel_8_026","t":0,"sx":661,"sy":1363,"sw":64,"sh":23,"dy":41,"dw":64,"dh":64},{"n":"sco_panel_8_027","t":0,"sx":265,"sy":1533,"sw":64,"sh":18,"dy":46,"dw":64,"dh":64},{"n":"sco_panel_8_028","t":0,"sx":595,"sy":1385,"sw":64,"sh":23,"dy":41,"dw":64,"dh":64},{"n":"sco_panel_8_029","t":0,"sx":727,"sy":1337,"sw":64,"sh":24,"dy":40,"dw":64,"dh":64},{"n":"sco_panel_8_030","t":0,"sx":331,"sy":1419,"sw":64,"sh":24,"dy":40,"dw":64,"dh":64},{"n":"sco_panel_8_031","t":0,"sx":529,"sy":1404,"sw":64,"sh":23,"dy":41,"dw":64,"dh":64},{"n":"sco_panel_8_032","t":0,"sx":463,"sy":1425,"sw":64,"sh":23,"dy":41,"dw":64,"dh":64},{"n":"sco_panel_8_033","t":0,"sx":1014,"sy":727,"sw":9,"sh":22,"dx":55,"dy":42,"dw":64,"dh":64},{"n":"sco_panel_8_034","t":0,"sx":463,"sy":1450,"sw":64,"sh":22,"dy":42,"dw":64,"dh":64},{"n":"sco_panel_8_035","t":0,"sx":463,"sy":331,"sw":64,"sh":64,"dw":64,"dh":64},{"n":"sco_panel_8_036","t":0,"sx":529,"sy":331,"sw":64,"sh":64,"dw":64,"dh":64},{"n":"sco_panel_8_037","t":0,"sx":911,"sy":1854,"sw":57,"sh":64,"dx":7,"dw":64,"dh":64},{"n":"sco_panel_8_038","t":0,"sx":595,"sy":331,"sw":64,"sh":64,"dw":64,"dh":64},{"n":"sco_panel_8_039","t":0,"sx":1,"sy":1926,"sw":57,"sh":64,"dw":64,"dh":64},{"n":"sco_panel_8_040","t":0,"sx":462,"sy":1609,"sw":63,"sh":64,"dw":64,"dh":64},{"n":"sco_panel_8_041","t":0,"sx":726,"sy":1600,"sw":63,"sh":64,"dx":1,"dw":64,"dh":64},{"n":"sco_panel_8_042","t":0,"sx":661,"sy":331,"sw":64,"sh":64,"dw":64,"dh":64},{"n":"sco_panel_8_043","t":0,"sx":791,"sy":1604,"sw":63,"sh":64,"dx":1,"dw":64,"dh":64},{"n":"sco_panel_8_044","t":0,"sx":661,"sy":1541,"sw":64,"sh":14,"dy":50,"dw":64,"dh":64},{"n":"sco_panel_8_045","t":0,"sx":991,"sy":785,"sw":18,"sh":11,"dy":53,"dw":64,"dh":64},{"n":"sco_panel_8_046","t":0,"sx":991,"sy":957,"sw":9,"sh":9,"dx":55,"dw":64,"dh":64},{"n":"sco_panel_8_047","t":0,"sx":727,"sy":331,"sw":64,"sh":64,"dw":64,"dh":64},{"n":"sco_panel_8_048","t":0,"sx":793,"sy":331,"sw":64,"sh":64,"dw":64,"dh":64},{"n":"sco_panel_8_049","t":0,"sx":859,"sy":331,"sw":64,"sh":64,"dw":64,"dh":64},{"n":"sco_panel_8_050","t":0,"sx":925,"sy":331,"sw":64,"sh":64,"dw":64,"dh":64},{"n":"sco_panel_8_051","t":0,"sx":1,"sy":397,"sw":64,"sh":64,"dw":64,"dh":64},{"n":"sco_panel_8_052","t":0,"sx":67,"sy":397,"sw":64,"sh":64,"dw":64,"dh":64},{"n":"sco_panel_8_053","t":0,"sx":133,"sy":397,"sw":64,"sh":64,"dw":64,"dh":64},{"n":"sco_panel_8_054","t":0,"sx":199,"sy":397,"sw":64,"sh":64,"dw":64,"dh":64},{"n":"sco_panel_8_055","t":0,"sx":265,"sy":397,"sw":64,"sh":64,"dw":64,"dh":64},{"n":"sco_panel_8_056","t":0,"sx":331,"sy":397,"sw":64,"sh":64,"dw":64,"dh":64},{"n":"sco_panel_8_057","t":0,"sx":397,"sy":397,"sw":64,"sh":64,"dw":64,"dh":64},{"n":"sco_panel_8_058","t":0,"sx":991,"sy":700,"sw":22,"sh":8,"dw":64,"dh":64},{"n":"sco_panel_8_059","t":0,"sx":516,"sy":1768,"sw":53,"sh":16,"dx":11,"dw":64,"dh":64},{"n":"sco_panel_8_060","t":0,"sx":189,"sy":1791,"sw":55,"sh":21,"dx":9,"dw":64,"dh":64},{"n":"sco_panel_8_061","t":0,"sx":331,"sy":1042,"sw":64,"sh":51,"dw":64,"dh":64},{"n":"sco_panel_8_062","t":0,"sx":397,"sy":1042,"sw":64,"sh":51,"dw":64,"dh":64},{"n":"sco_panel_8_063","t":0,"sx":1,"sy":1043,"sw":64,"sh":51,"dw":64,"dh":64},{"n":"sco_panel_8_064","t":0,"sx":67,"sy":1043,"sw":64,"sh":51,"dw":64,"dh":64},{"n":"sco_panel_8_065","t":0,"sx":859,"sy":769,"sw":64,"sh":57,"dw":64,"dh":64},{"n":"sco_panel_8_066","t":0,"sx":133,"sy":1043,"sw":64,"sh":51,"dw":64,"dh":64},{"n":"sco_panel_8_067","t":0,"sx":199,"sy":1043,"sw":64,"sh":51,"dw":64,"dh":64},{"n":"sco_panel_8_068","t":0,"sx":197,"sy":1599,"sw":63,"sh":21,"dw":64,"dh":64},{"n":"sco_panel_8_069","t":0,"sx":133,"sy":1555,"sw":64,"sh":16,"dw":64,"dh":64},{"n":"sco_panel_8_070","t":0,"sx":1021,"sy":312,"sw":2,"sh":13,"dy":2,"dw":64,"dh":64},{"n":"sco_panel_8_071","t":0,"sx":991,"sy":256,"sw":29,"sh":24,"dx":35,"dy":33,"dw":64,"dh":64},{"n":"sco_panel_8_072","t":0,"sx":1,"sy":1253,"sw":64,"sh":26,"dy":32,"dw":64,"dh":64},{"n":"sco_panel_8_073","t":0,"sx":133,"sy":1160,"sw":64,"sh":30,"dy":33,"dw":64,"dh":64},{"n":"sco_panel_8_074","t":0,"sx":727,"sy":1310,"sw":64,"sh":25,"dy":33,"dw":64,"dh":64},{"n":"sco_panel_8_075","t":0,"sx":463,"sy":1172,"sw":64,"sh":31,"dy":33,"dw":64,"dh":64},{"n":"sco_panel_8_076","t":0,"sx":331,"sy":1392,"sw":64,"sh":25,"dy":33,"dw":64,"dh":64},{"n":"sco_panel_8_077","t":0,"sx":529,"sy":1178,"sw":64,"sh":31,"dy":33,"dw":64,"dh":64},{"n":"sco_panel_8_078","t":0,"sx":133,"sy":1192,"sw":64,"sh":29,"dy":33,"dw":64,"dh":64},{"n":"sco_panel_8_079","t":0,"sx":199,"sy":1160,"sw":64,"sh":30,"dy":33,"dw":64,"dh":64},{"n":"sco_panel_8_080","t":0,"sx":265,"sy":1417,"sw":64,"sh":25,"dy":38,"dw":64,"dh":64},{"n":"sco_panel_8_081","t":0,"sx":199,"sy":1441,"sw":64,"sh":25,"dy":33,"dw":64,"dh":64},{"n":"sco_panel_8_082","t":0,"sx":265,"sy":1164,"sw":64,"sh":30,"dy":33,"dw":64,"dh":64},{"n":"sco_panel_8_083","t":0,"sx":357,"sy":1821,"sw":44,"sh":25,"dy":38,"dw":64,"dh":64},{"n":"sco_panel_8_084","t":0,"sx":375,"sy":1761,"sw":50,"sh":20,"dx":14,"dy":10,"dw":64,"dh":64},{"n":"sco_panel_8_085","t":0,"sx":397,"sy":1392,"sw":64,"sh":25,"dy":5,"dw":64,"dh":64},{"n":"sco_panel_8_086","t":0,"sx":67,"sy":1442,"sw":64,"sh":25,"dy":5,"dw":64,"dh":64},{"n":"sco_panel_8_087","t":0,"sx":133,"sy":1494,"sw":64,"sh":20,"dy":10,"dw":64,"dh":64},{"n":"sco_panel_8_088","t":0,"sx":397,"sy":1444,"sw":64,"sh":23,"dy":7,"dw":64,"dh":64},{"n":"sco_panel_8_089","t":0,"sx":331,"sy":1491,"sw":64,"sh":20,"dy":10,"dw":64,"dh":64},{"n":"sco_panel_8_090","t":0,"sx":66,"sy":1600,"sw":63,"sh":20,"dy":10,"dw":64,"dh":64},{"n":"sco_panel_8_091","t":0,"sx":1,"sy":1096,"sw":64,"sh":31,"dy":5,"dw":64,"dh":64},{"n":"sco_panel_8_092","t":0,"sx":67,"sy":1573,"sw":63,"sh":25,"dy":5,"dw":64,"dh":64},{"n":"sco_panel_8_093","t":0,"sx":1015,"sy":702,"sw":8,"sh":23,"dx":56,"dy":13,"dw":64,"dh":64},{"n":"sco_panel_8_094","t":0,"sx":1,"sy":1574,"sw":63,"sh":25,"dy":12,"dw":64,"dh":64},{"n":"sco_panel_8_095","t":0,"sx":154,"sy":1992,"sw":56,"sh":26,"dx":8,"dy":11,"dw":64,"dh":64},{"n":"sco_panel_8_096","t":0,"sx":199,"sy":1192,"sw":64,"sh":29,"dy":12,"dw":64,"dh":64},{"n":"sco_panel_8_097","t":0,"sx":1,"sy":1443,"sw":64,"sh":25,"dy":12,"dw":64,"dh":64},{"n":"sco_panel_8_098","t":0,"sx":397,"sy":1491,"sw":64,"sh":20,"dy":17,"dw":64,"dh":64},{"n":"sco_panel_8_099","t":0,"sx":64,"sy":1757,"sw":60,"sh":30,"dy":12,"dw":64,"dh":64},{"n":"sco_panel_8_100","t":0,"sx":132,"sy":1573,"sw":63,"sh":25,"dx":1,"dy":17,"dw":64,"dh":64},{"n":"sco_panel_8_101","t":0,"sx":265,"sy":1196,"sw":64,"sh":28,"dy":12,"dw":64,"dh":64},{"n":"sco_panel_8_102","t":0,"sx":133,"sy":1252,"sw":64,"sh":26,"dy":17,"dw":64,"dh":64},{"n":"sco_panel_8_103","t":0,"sx":331,"sy":1167,"sw":64,"sh":30,"dy":12,"dw":64,"dh":64},{"n":"sco_panel_8_104","t":0,"sx":133,"sy":1442,"sw":64,"sh":25,"dy":12,"dw":64,"dh":64},{"n":"sco_panel_8_105","t":0,"sx":991,"sy":742,"sw":19,"sh":19,"dx":1,"dy":17,"dw":64,"dh":64},{"n":"sco_panel_8_106","t":0,"sx":472,"sy":1783,"sw":42,"sh":9,"dx":22,"dy":55,"dw":64,"dh":64},{"n":"sco_panel_8_107","t":0,"sx":529,"sy":1575,"sw":64,"sh":9,"dy":55,"dw":64,"dh":64},{"n":"sco_panel_8_108","t":0,"sx":925,"sy":1560,"sw":64,"sh":9,"dy":55,"dw":64,"dh":64},{"n":"sco_panel_8_109","t":0,"sx":1,"sy":1619,"sw":63,"sh":9,"dx":1,"dy":55,"dw":64,"dh":64},{"n":"sco_panel_8_110","t":0,"sx":859,"sy":1570,"sw":64,"sh":9,"dy":55,"dw":64,"dh":64},{"n":"sco_panel_8_111","t":0,"sx":793,"sy":1578,"sw":64,"sh":9,"dy":55,"dw":64,"dh":64},{"n":"sco_panel_8_112","t":0,"sx":195,"sy":1680,"sw":62,"sh":10,"dy":54,"dw":64,"dh":64},{"n":"sco_panel_8_113","t":0,"sx":363,"sy":1783,"sw":57,"sh":9,"dx":7,"dy":55,"dw":64,"dh":64},{"n":"sco_panel_8_114","t":0,"sx":131,"sy":1600,"sw":63,"sh":9,"dy":55,"dw":64,"dh":64},{"n":"sco_panel_8_115","t":0,"sx":727,"sy":1579,"sw":64,"sh":9,"dy":55,"dw":64,"dh":64},{"n":"sco_panel_8_116","t":0,"sx":422,"sy":1783,"sw":48,"sh":9,"dy":55,"dw":64,"dh":64},{"n":"sco_panel_8_117","t":0,"sx":164,"sy":2030,"sw":42,"sh":16,"dx":22,"dw":64,"dh":64},{"n":"sco_panel_8_118","t":0,"sx":595,"sy":1541,"sw":64,"sh":16,"dw":64,"dh":64},{"n":"sco_panel_8_119","t":0,"sx":529,"sy":1557,"sw":64,"sh":16,"dw":64,"dh":64},{"n":"sco_panel_8_120","t":0,"sx":262,"sy":1591,"sw":63,"sh":22,"dx":1,"dw":64,"dh":64},{"n":"sco_panel_8_121","t":0,"sx":463,"sy":1574,"sw":64,"sh":16,"dw":64,"dh":64},{"n":"sco_panel_8_122","t":0,"sx":397,"sy":1589,"sw":64,"sh":16,"dw":64,"dh":64},{"n":"sco_panel_8_123","t":0,"sx":327,"sy":1608,"sw":63,"sh":21,"dw":64,"dh":64},{"n":"sco_panel_8_124","t":0,"sx":312,"sy":1855,"sw":57,"sh":16,"dx":7,"dw":64,"dh":64},{"n":"sco_panel_8_125","t":0,"sx":1,"sy":1601,"sw":63,"sh":16,"dw":64,"dh":64},{"n":"sco_panel_8_126","t":0,"sx":331,"sy":1590,"sw":64,"sh":16,"dw":64,"dh":64},{"n":"sco_panel_8_127","t":0,"sx":63,"sy":1798,"sw":57,"sh":15,"dw":64,"dh":64}]}