{"ts":["translate_rgba-0-en:2048x2048","translate_rgba-1-en:2048x2048","translate_rgba-2-en:1024x2048"],"ss":[{"n":"12c_shop_buy_disable","t":0,"sx":693,"sy":1971,"sw":140,"sh":69,"dx":32,"dy":28,"dw":204,"dh":119},{"n":"12c_shop_buy_onpress","t":0,"sx":1193,"sy":1983,"sw":130,"sh":64,"dx":37,"dy":30,"dw":204,"dh":119},{"n":"12c_shop_hold_the_jackpot","t":0,"sx":894,"sy":706,"sw":1051,"sh":85,"dw":1054,"dh":85},{"n":"16Coins_logo_horizontal_small","t":0,"sx":893,"sy":1779,"sw":443,"sh":202,"dx":25,"dw":501,"dh":219},{"n":"16c_content","t":0,"sx":1,"sy":928,"sw":1550,"sh":447,"dy":6,"dw":1550,"dh":460},{"n":"16c_content_mobile","t":0,"sx":1,"sy":1,"sw":891,"sh":925,"dx":45,"dy":30,"dw":998,"dh":1027},{"n":"16c_hold_on","t":0,"sx":1,"sy":1730,"sw":1400,"sh":47,"dx":22,"dy":32,"dw":1444,"dh":111},{"n":"16c_hold_on_mobile","t":0,"sx":894,"sy":793,"sw":768,"sh":105,"dx":41,"dy":37,"dw":850,"dh":167},{"n":"16c_sp_cash_infinity","t":0,"sx":1664,"sy":793,"sw":332,"sh":49,"dx":231,"dy":10,"dw":794,"dh":66},{"n":"16c_sp_do_not_show_again","t":0,"sx":1664,"sy":844,"sw":359,"sh":29,"dx":1,"dy":10,"dw":361,"dh":48},{"n":"16c_sp_txt_gamble","t":0,"sx":835,"sy":1983,"sw":356,"sh":47,"dx":219,"dy":11,"dw":794,"dh":66},{"n":"16c_sp_txt_hold_the_jackpot","t":0,"sx":1,"sy":1971,"sw":690,"sh":49,"dx":52,"dy":10,"dw":794,"dh":66},{"n":"9c_continue_disable","t":0,"sx":1553,"sy":1206,"sw":402,"sh":154,"dy":7,"dw":402,"dh":168},{"n":"9c_gamble_guess","t":0,"sx":1325,"sy":1997,"sw":508,"sh":45,"dx":58,"dy":15,"dw":622,"dh":76},{"n":"9c_gamble_round","t":0,"sx":1835,"sy":1997,"sw":212,"sh":47,"dx":59,"dy":10,"dw":328,"dh":68},{"n":"9c_gj_bonus_blur","t":0,"sx":1338,"sy":1832,"sw":660,"sh":163,"dx":171,"dy":91,"dw":1002,"dh":347},{"n":"9c_gj_jackpot_blur","t":0,"sx":1,"sy":1779,"sw":890,"sh":190,"dx":59,"dy":52,"dw":1008,"dh":294},{"n":"9c_htjb","t":0,"sx":1,"sy":1377,"sw":1401,"sh":152,"dx":59,"dw":1518,"dh":152},{"n":"9c_jackpot_mask_grand","t":0,"sx":1884,"sy":1171,"sw":132,"sh":23,"dw":132,"dh":23},{"n":"9c_sym_jackpotmystery_blur","t":0,"sx":1553,"sy":900,"sw":329,"sh":304,"dw":329,"dh":304},{"n":"scge_hor_chance_level_frame","t":0,"sx":1803,"sy":1,"sw":147,"sh":674,"dw":147,"dh":674},{"n":"scge_hor_total_bet","t":0,"sx":1945,"sy":677,"sw":102,"sh":18,"dx":23,"dy":10,"dw":147,"dh":114},{"n":"scge_hor_total_bet_icon","t":0,"sx":1952,"sy":60,"sw":55,"sh":49,"dx":46,"dy":4,"dw":147,"dh":114},{"n":"scge_ver_chance_level_frame","t":0,"sx":1,"sy":1531,"sw":1160,"sh":197,"dw":1160,"dh":197},{"n":"scge_ver_total_bet","t":0,"sx":1803,"sy":677,"sw":140,"sh":25,"dx":65,"dy":78,"dw":275,"dh":197},{"n":"scge_ver_total_bet_icon","t":0,"sx":1952,"sy":1,"sw":65,"sh":57,"dx":106,"dy":66,"dw":275,"dh":197},{"n":"sco_grand_jackpot","t":0,"sx":1404,"sy":1377,"sw":516,"sh":453,"dx":1,"dy":2,"dw":519,"dh":456},{"n":"sco_hor_off_disabled","t":0,"sx":1922,"sy":1362,"sw":119,"sh":94,"dx":19,"dy":9,"dw":157,"dh":109},{"n":"sco_hor_off_normal","t":0,"sx":1922,"sy":1458,"sw":119,"sh":94,"dx":19,"dy":9,"dw":157,"dh":109},{"n":"sco_hor_off_onhover","t":0,"sx":1922,"sy":1554,"sw":119,"sh":94,"dx":19,"dy":9,"dw":157,"dh":109},{"n":"sco_hor_x10_disabled","t":0,"sx":1922,"sy":1650,"sw":119,"sh":94,"dx":19,"dy":9,"dw":157,"dh":109},{"n":"sco_ver_x10_active","t":0,"sx":1884,"sy":875,"sw":163,"sh":146,"dw":163,"dh":146},{"n":"sco_ver_x2_active","t":0,"sx":1884,"sy":1023,"sw":163,"sh":146,"dw":163,"dh":146},{"n":"sco_ver_x4_active","t":0,"sx":1163,"sy":1531,"sw":163,"sh":146,"dw":163,"dh":146},{"n":"stamp_bottom1","t":0,"sx":894,"sy":1,"sw":907,"sh":703,"dw":907,"dh":703},{"n":"tfc_logo_htj_txt","t":0,"sx":1163,"sy":1679,"sw":235,"sh":42,"dw":235,"dh":42},{"n":"12c_jackpot_frame_grand","t":1,"sx":1611,"sy":1138,"sw":312,"sh":163,"dx":38,"dy":1,"dw":394,"dh":166},{"n":"12c_logo_cash_infinity_txt_mobile","t":1,"sx":284,"sy":2013,"sw":238,"sh":28,"dw":238,"dh":28},{"n":"12c_logo_hold_the_jackpot_txt_mobile","t":1,"sx":1,"sy":2013,"sw":281,"sh":28,"dx":1,"dy":2,"dw":282,"dh":32},{"n":"12c_shop_buy_normal","t":1,"sx":793,"sy":1972,"sw":140,"sh":69,"dx":32,"dy":28,"dw":204,"dh":119},{"n":"12c_shop_buy_onhover","t":1,"sx":1689,"sy":1899,"sw":140,"sh":69,"dx":32,"dy":28,"dw":204,"dh":119},{"n":"16c_logo_htj","t":1,"sx":542,"sy":1991,"sw":246,"sh":44,"dx":4,"dw":250,"dh":46},{"n":"16c_logo_vertical_small","t":1,"sx":1,"sy":1262,"sw":570,"sh":439,"dw":570,"dh":439},{"n":"16c_sp_slide_hold_the_jackpot_1","t":1,"sx":1,"sy":706,"sw":940,"sh":554,"dw":940,"dh":554},{"n":"16c_sp_slide_hold_the_jackpot_2","t":1,"sx":910,"sy":1,"sw":940,"sh":554,"dw":940,"dh":554},{"n":"16c_sp_txt_buy_feature","t":1,"sx":1363,"sy":1979,"sw":274,"sh":47,"dx":260,"dy":11,"dw":794,"dh":66},{"n":"16c_sp_txt_chance_level","t":1,"sx":1363,"sy":1928,"sw":324,"sh":49,"dx":235,"dy":10,"dw":794,"dh":66},{"n":"9c_congratulations_end","t":1,"sx":1474,"sy":557,"sw":545,"sh":120,"dx":69,"dy":43,"dw":682,"dh":206},{"n":"9c_continue_normal","t":1,"sx":1611,"sy":1303,"sw":402,"sh":154,"dy":7,"dw":402,"dh":168},{"n":"9c_continue_onhover","t":1,"sx":1611,"sy":1459,"sw":402,"sh":154,"dy":7,"dw":402,"dh":168},{"n":"9c_gj_bonus","t":1,"sx":910,"sy":557,"sw":562,"sh":139,"dw":562,"dh":139},{"n":"9c_gj_jackpot","t":1,"sx":938,"sy":1766,"sw":746,"sh":160,"dw":746,"dh":160},{"n":"9c_gj_jackpot_glow","t":1,"sx":1,"sy":1703,"sw":820,"sh":233,"dw":820,"dh":233},{"n":"9c_jackpot_bonus_respins_mobile","t":1,"sx":938,"sy":1928,"sw":423,"sh":72,"dx":22,"dy":9,"dw":467,"dh":90},{"n":"9c_jackpot_bonus_total win_mobile","t":1,"sx":1,"sy":1938,"sw":539,"sh":73,"dx":21,"dy":9,"dw":580,"dh":90},{"n":"9c_jackpot_frame_major","t":1,"sx":573,"sy":1548,"sw":357,"sh":152,"dx":1,"dy":1,"dw":360,"dh":155},{"n":"9c_jackpot_frame_mini_mobile","t":1,"sx":1686,"sy":1758,"sw":320,"sh":139,"dx":1,"dy":1,"dw":323,"dh":142},{"n":"9c_jackpot_frame_minor","t":1,"sx":1611,"sy":1615,"sw":327,"sh":141,"dx":1,"dy":1,"dw":330,"dh":144},{"n":"9c_repsin_label_respins","t":1,"sx":935,"sy":2002,"sw":212,"sh":38,"dw":212,"dh":38},{"n":"9c_repsin_label_total_win","t":1,"sx":1639,"sy":1979,"sw":217,"sh":31,"dw":217,"dh":31},{"n":"9c_sym_jackpot_mask","t":1,"sx":542,"sy":1938,"sw":249,"sh":51,"dw":249,"dh":51},{"n":"9c_sym_jackpotmystery_disable","t":1,"sx":573,"sy":1262,"sw":335,"sh":284,"dw":335,"dh":284},{"n":"9c_sym_jackpotmystery_static","t":1,"sx":1611,"sy":679,"sw":335,"sh":284,"dw":335,"dh":284},{"n":"extreme_votatility_5p","t":1,"sx":943,"sy":698,"sw":666,"sh":532,"dw":666,"dh":532},{"n":"extreme_votatility_sc_4peppers","t":1,"sx":943,"sy":1232,"sw":666,"sh":532,"dw":666,"dh":532},{"n":"sco_grand_frame","t":1,"sx":1611,"sy":965,"sw":417,"sh":171,"dw":417,"dh":171},{"n":"sco_hor_off_onpress","t":1,"sx":823,"sy":1702,"sw":113,"sh":88,"dx":22,"dy":12,"dw":157,"dh":109},{"n":"sco_hor_x10_disabled_dark","t":1,"sx":1925,"sy":1138,"sw":119,"sh":94,"dx":19,"dy":9,"dw":157,"dh":109},{"n":"sco_hor_x10_onpress","t":1,"sx":823,"sy":1792,"sw":113,"sh":88,"dx":22,"dy":12,"dw":157,"dh":109},{"n":"sco_hor_x2_onpress","t":1,"sx":823,"sy":1882,"sw":113,"sh":88,"dx":22,"dy":12,"dw":157,"dh":109},{"n":"sco_ver_x10_disabled","t":1,"sx":1852,"sy":149,"sw":150,"sh":119,"dx":6,"dy":13,"dw":163,"dh":146},{"n":"sco_ver_x10_disabled_dark","t":1,"sx":1852,"sy":270,"sw":150,"sh":119,"dx":6,"dy":13,"dw":163,"dh":146},{"n":"sco_ver_x10_normal","t":1,"sx":1852,"sy":391,"sw":150,"sh":119,"dx":6,"dy":13,"dw":163,"dh":146},{"n":"sco_ver_x10_onhover","t":1,"sx":1858,"sy":1899,"sw":150,"sh":119,"dx":6,"dy":13,"dw":163,"dh":146},{"n":"sco_ver_x6_active","t":1,"sx":1852,"sy":1,"sw":163,"sh":146,"dw":163,"dh":146},{"n":"stamp_bottom_doubleextreme_5","t":1,"sx":1,"sy":1,"sw":907,"sh":703,"dw":907,"dh":703},{"n":"16Coins_logo_small","t":2,"sx":1,"sy":203,"sw":576,"sh":411,"dw":576,"dh":426},{"n":"9c_continue_onpress","t":2,"sx":579,"sy":297,"sw":402,"sh":154,"dy":7,"dw":402,"dh":168},{"n":"9c_gj_bonus_glow","t":2,"sx":1,"sy":1,"sw":625,"sh":200,"dw":625,"dh":200},{"n":"9c_jackpot_frame_grand","t":2,"sx":628,"sy":1,"sw":371,"sh":153,"dx":10,"dy":4,"dw":394,"dh":166},{"n":"9c_jackpot_frame_major_mobile","t":2,"sx":579,"sy":453,"sw":319,"sh":139,"dx":1,"dy":1,"dw":322,"dh":142},{"n":"9c_jackpot_frame_mini","t":2,"sx":579,"sy":594,"sw":294,"sh":130,"dx":1,"dy":1,"dw":297,"dh":133},{"n":"9c_jackpot_frame_minor_mobile","t":2,"sx":628,"sy":156,"sw":320,"sh":139,"dx":1,"dy":1,"dw":323,"dh":142},{"n":"9c_sym_jackpot","t":2,"sx":1,"sy":616,"sw":280,"sh":82,"dw":280,"dh":82},{"n":"sco_hor_off_active","t":2,"sx":153,"sy":1248,"sw":149,"sh":109,"dx":4,"dw":157,"dh":109},{"n":"sco_hor_x10_active","t":2,"sx":810,"sy":760,"sw":157,"sh":109,"dw":157,"dh":109},{"n":"sco_hor_x10_normal","t":2,"sx":900,"sy":453,"sw":119,"sh":94,"dx":19,"dy":9,"dw":157,"dh":109},{"n":"sco_hor_x10_onhover","t":2,"sx":900,"sy":549,"sw":119,"sh":94,"dx":19,"dy":9,"dw":157,"dh":109},{"n":"sco_hor_x2_active","t":2,"sx":517,"sy":847,"sw":157,"sh":109,"dw":157,"dh":109},{"n":"sco_hor_x2_disabled","t":2,"sx":676,"sy":847,"sw":119,"sh":94,"dx":19,"dy":9,"dw":157,"dh":109},{"n":"sco_hor_x2_disabled_dark","t":2,"sx":676,"sy":943,"sw":119,"sh":94,"dx":19,"dy":9,"dw":157,"dh":109},{"n":"sco_hor_x2_normal","t":2,"sx":672,"sy":1039,"sw":119,"sh":94,"dx":19,"dy":9,"dw":157,"dh":109},{"n":"sco_hor_x2_onhover","t":2,"sx":672,"sy":1135,"sw":119,"sh":94,"dx":19,"dy":9,"dw":157,"dh":109},{"n":"sco_hor_x4_active","t":2,"sx":797,"sy":871,"sw":157,"sh":109,"dw":157,"dh":109},{"n":"sco_hor_x4_disabled","t":2,"sx":304,"sy":1321,"sw":119,"sh":94,"dx":19,"dy":9,"dw":157,"dh":109},{"n":"sco_hor_x4_disabled_dark","t":2,"sx":147,"sy":1359,"sw":119,"sh":94,"dx":19,"dy":9,"dw":157,"dh":109},{"n":"sco_hor_x4_normal","t":2,"sx":1,"sy":1414,"sw":119,"sh":94,"dx":19,"dy":9,"dw":157,"dh":109},{"n":"sco_hor_x4_onhover","t":2,"sx":755,"sy":1335,"sw":119,"sh":94,"dx":19,"dy":9,"dw":157,"dh":109},{"n":"sco_hor_x4_onpress","t":2,"sx":557,"sy":958,"sw":113,"sh":88,"dx":22,"dy":12,"dw":157,"dh":109},{"n":"sco_hor_x6_active","t":2,"sx":797,"sy":982,"sw":157,"sh":109,"dw":157,"dh":109},{"n":"sco_hor_x6_disabled","t":2,"sx":876,"sy":1335,"sw":119,"sh":94,"dx":19,"dy":9,"dw":157,"dh":109},{"n":"sco_hor_x6_disabled_dark","t":2,"sx":603,"sy":1346,"sw":119,"sh":94,"dx":19,"dy":9,"dw":157,"dh":109},{"n":"sco_hor_x6_normal","t":2,"sx":425,"sy":1374,"sw":119,"sh":94,"dx":19,"dy":9,"dw":157,"dh":109},{"n":"sco_hor_x6_onhover","t":2,"sx":268,"sy":1417,"sw":119,"sh":94,"dx":19,"dy":9,"dw":157,"dh":109},{"n":"sco_hor_x6_onpress","t":2,"sx":557,"sy":1048,"sw":113,"sh":88,"dx":22,"dy":12,"dw":157,"dh":109},{"n":"sco_ver_off_active","t":2,"sx":283,"sy":616,"sw":267,"sh":146,"dw":267,"dh":146},{"n":"sco_ver_off_disabled","t":2,"sx":1,"sy":700,"sw":256,"sh":119,"dx":7,"dy":13,"dw":267,"dh":146},{"n":"sco_ver_off_normal","t":2,"sx":552,"sy":726,"sw":256,"sh":119,"dx":7,"dy":13,"dw":267,"dh":146},{"n":"sco_ver_off_onhover","t":2,"sx":259,"sy":764,"sw":256,"sh":119,"dx":7,"dy":13,"dw":267,"dh":146},{"n":"sco_ver_off_onpress","t":2,"sx":1,"sy":821,"sw":250,"sh":113,"dx":10,"dy":16,"dw":267,"dh":146},{"n":"sco_ver_x10_onpress","t":2,"sx":875,"sy":645,"sw":144,"sh":113,"dx":9,"dy":16,"dw":163,"dh":146},{"n":"sco_ver_x2_disabled","t":2,"sx":253,"sy":885,"sw":150,"sh":119,"dx":6,"dy":13,"dw":163,"dh":146},{"n":"sco_ver_x2_disabled_dark","t":2,"sx":1,"sy":936,"sw":150,"sh":119,"dx":6,"dy":13,"dw":163,"dh":146},{"n":"sco_ver_x2_normal","t":2,"sx":405,"sy":958,"sw":150,"sh":119,"dx":6,"dy":13,"dw":163,"dh":146},{"n":"sco_ver_x2_onhover","t":2,"sx":793,"sy":1093,"sw":150,"sh":119,"dx":6,"dy":13,"dw":163,"dh":146},{"n":"sco_ver_x2_onpress","t":2,"sx":1,"sy":1299,"sw":144,"sh":113,"dx":9,"dy":16,"dw":163,"dh":146},{"n":"sco_ver_x4_disabled","t":2,"sx":793,"sy":1214,"sw":150,"sh":119,"dx":6,"dy":13,"dw":163,"dh":146},{"n":"sco_ver_x4_disabled_dark","t":2,"sx":153,"sy":1006,"sw":150,"sh":119,"dx":6,"dy":13,"dw":163,"dh":146},{"n":"sco_ver_x4_normal","t":2,"sx":1,"sy":1057,"sw":150,"sh":119,"dx":6,"dy":13,"dw":163,"dh":146},{"n":"sco_ver_x4_onhover","t":2,"sx":305,"sy":1079,"sw":150,"sh":119,"dx":6,"dy":13,"dw":163,"dh":146},{"n":"sco_ver_x4_onpress","t":2,"sx":609,"sy":1231,"sw":144,"sh":113,"dx":9,"dy":16,"dw":163,"dh":146},{"n":"sco_ver_x6_disabled","t":2,"sx":153,"sy":1127,"sw":150,"sh":119,"dx":6,"dy":13,"dw":163,"dh":146},{"n":"sco_ver_x6_disabled_dark","t":2,"sx":1,"sy":1178,"sw":150,"sh":119,"dx":6,"dy":13,"dw":163,"dh":146},{"n":"sco_ver_x6_normal","t":2,"sx":457,"sy":1138,"sw":150,"sh":119,"dx":6,"dy":13,"dw":163,"dh":146},{"n":"sco_ver_x6_onhover","t":2,"sx":305,"sy":1200,"sw":150,"sh":119,"dx":6,"dy":13,"dw":163,"dh":146},{"n":"sco_ver_x6_onpress","t":2,"sx":457,"sy":1259,"sw":144,"sh":113,"dx":9,"dy":16,"dw":163,"dh":146}]}